{"status":"success","totalResults":1740,"results":[{"article_id":"71bcff78f5408e7adfdcfc188dfab85c","link":"https://news.walla.co.il/item/3846632","title":"אזהרת הרמטכ\"ל לדרג המדיני: \"הצבא יקרוס\" ללא הארכת שירות חובה","description":"בצה\"ל מזהירים כי השבועיים הקרובים קריטיים לאישור החקיקה שתמנע פער של מחזור גיוס שלם. הצבא סובל ממחסור של כ-12 אלף משרתים, והרמטכ\"ל התריע בפני השרים כי הוא \"מרים 12 דגלים אדומים\". החשש המרכזי הוא מפיזור הכנסת לפני סיום ההליך","content":"ONLY AVAILABLE IN PAID PLANS","keywords":null,"creator":["אבי סולומון"],"language":"hebrew","country":["israel"],"category":["crime","business","top"],"datatype":"news","pubDate":"2026-06-18 08:00:00","pubDateTZ":"UTC","fetched_at":"2026-06-18 11:34:50","image_url":"https://images.wcdn.co.il/f_auto,q_auto,w_1200,t_54/4/0/4/8/4048857-46.jpg","video_url":null,"source_id":"walla","source_name":"Walla!","source_priority":26977,"source_url":"https://www.walla.co.il","source_icon":"https://n.bytvi.com/walla.png","sentiment":"ONLY AVAILABLE IN PROFESSIONAL AND CORPORATE PLANS","sentiment_stats":"ONLY AVAILABLE IN PROFESSIONAL AND CORPORATE PLANS","ai_tag":"ONLY AVAILABLE IN PROFESSIONAL AND CORPORATE PLANS","ai_region":"ONLY AVAILABLE IN CORPORATE PLANS","ai_org":"ONLY AVAILABLE IN CORPORATE PLANS","ai_summary":"ONLY AVAILABLE IN PAID PLANS","duplicate":false},{"article_id":"daf249ba5df6d208fdf081f52f734025","link":"https://www.israelhayom.co.il/sport/world-soccer/article/20788651","title":"צפו בתקציר: 2:4 מטורף לאנגליה על קרואטיה","description":"שני קאמבקים של הקרואטים, צמד של הארי קיין וחגיגה של שערים במשחק הטוב ביותר עד כה במונדיאל 2026","content":"ONLY AVAILABLE IN PAID PLANS","keywords":["נבחרת אנגליה","תקצירי מונדיאל 2026","הארי קיין","מונדיאל 2026"],"creator":["מערכת ספורט היום"],"language":"hebrew","country":["israel"],"category":["sports","top"],"datatype":"news","pubDate":"2026-06-18 07:59:23","pubDateTZ":"UTC","fetched_at":"2026-06-18 08:03:26","image_url":"https://www.israelhayom.co.il/wp-content/uploads/2026/06/18/18/New_AFP_B7G37RR.jpg","video_url":null,"source_id":"israelhayom","source_name":"ישראל היום","source_priority":13660,"source_url":"https://www.israelhayom.co.il","source_icon":"https://n.bytvi.com/israelhayom.jpg","sentiment":"ONLY AVAILABLE IN PROFESSIONAL AND CORPORATE PLANS","sentiment_stats":"ONLY AVAILABLE IN PROFESSIONAL AND CORPORATE PLANS","ai_tag":"ONLY AVAILABLE IN PROFESSIONAL AND CORPORATE PLANS","ai_region":"ONLY AVAILABLE IN CORPORATE PLANS","ai_org":"ONLY AVAILABLE IN CORPORATE PLANS","ai_summary":"ONLY AVAILABLE IN PAID PLANS","duplicate":false},{"article_id":"0f7c66a73458775a843e4f3cd931a5a9","link":"https://il.investing.com/news/stock-market-news/article-93CH-882680","title":"מדוע מניית FirstGroup זינקה היום?","description":null,"content":"ONLY AVAILABLE IN PAID PLANS","keywords":null,"creator":null,"language":"hebrew","country":["israel"],"category":["entertainment","top"],"datatype":"news","pubDate":"2026-06-18 07:58:41","pubDateTZ":"UTC","fetched_at":"2026-06-18 08:31:48","image_url":null,"video_url":null,"source_id":"investing_il","source_name":"Investing","source_priority":1143,"source_url":"https://il.investing.com","source_icon":"https://n.bytvi.com/investing_il.png","sentiment":"ONLY AVAILABLE IN PROFESSIONAL AND CORPORATE PLANS","sentiment_stats":"ONLY AVAILABLE IN PROFESSIONAL AND CORPORATE PLANS","ai_tag":"ONLY AVAILABLE IN PROFESSIONAL AND CORPORATE PLANS","ai_region":"ONLY AVAILABLE IN CORPORATE PLANS","ai_org":"ONLY AVAILABLE IN CORPORATE PLANS","ai_summary":"ONLY AVAILABLE IN PAID PLANS","duplicate":false},{"article_id":"7b11101334a272ecf6963f07eeb506a0","link":"https://www.inn.co.il/news/699298","title":"המילואימניק שמציע סדר חדש | פודקאסט חדש עם עוז בן נון","description":"מנכ\"ל מרכז 'ריבוא' קורא להפסיק את ההתרפסות בפני המגזר החרדי, לשנות את חוקי המשחק הכלכליים ולהגדיר מחדש מי ראוי להוביל את המדינה","content":"ONLY AVAILABLE IN PAID PLANS","keywords":["אולפן ערוץ 7","פודקאסטים","עוזי ברוך"],"creator":["עוזי ברוך"],"language":"hebrew","country":["israel"],"category":["politics","top"],"datatype":"news","pubDate":"2026-06-18 07:57:18","pubDateTZ":"UTC","fetched_at":"2026-06-18 08:09:57","image_url":"https://2.a7.org/files/pictures/000/undefined.jpg","video_url":null,"source_id":"inn","source_name":"Inn","source_priority":129730,"source_url":"https://www.inn.co.il","source_icon":"https://n.bytvi.com/inn.png","sentiment":"ONLY AVAILABLE IN PROFESSIONAL AND CORPORATE PLANS","sentiment_stats":"ONLY AVAILABLE IN PROFESSIONAL AND CORPORATE PLANS","ai_tag":"ONLY AVAILABLE IN PROFESSIONAL AND CORPORATE PLANS","ai_region":"ONLY AVAILABLE IN CORPORATE PLANS","ai_org":"ONLY AVAILABLE IN CORPORATE PLANS","ai_summary":"ONLY AVAILABLE IN PAID PLANS","duplicate":false},{"article_id":"fcc2b34b0f419414334fac74844272d7","link":"https://il.investing.com/news/stock-market-news/article-93CH-882679","title":"מדוע מניית BE Semiconductor עולה היום?","description":null,"content":"ONLY AVAILABLE IN PAID PLANS","keywords":null,"creator":null,"language":"hebrew","country":["israel"],"category":["technology","top"],"datatype":"news","pubDate":"2026-06-18 07:56:09","pubDateTZ":"UTC","fetched_at":"2026-06-18 08:02:46","image_url":null,"video_url":null,"source_id":"investing_il","source_name":"Investing","source_priority":1143,"source_url":"https://il.investing.com","source_icon":"https://n.bytvi.com/investing_il.png","sentiment":"ONLY AVAILABLE IN PROFESSIONAL AND CORPORATE PLANS","sentiment_stats":"ONLY AVAILABLE IN PROFESSIONAL AND CORPORATE PLANS","ai_tag":"ONLY AVAILABLE IN PROFESSIONAL AND CORPORATE PLANS","ai_region":"ONLY AVAILABLE IN CORPORATE PLANS","ai_org":"ONLY AVAILABLE IN CORPORATE PLANS","ai_summary":"ONLY AVAILABLE IN PAID PLANS","duplicate":false},{"article_id":"4148407d62ed24e371eaf4866ff1c55e","link":"https://il.investing.com/news/company-news/article-93CH-882678","title":"חברת INPP מינתה את קוקסון ליו\"ר Foresight Environmental","description":null,"content":"ONLY AVAILABLE IN PAID PLANS","keywords":null,"creator":null,"language":"hebrew","country":["israel"],"category":["politics","top"],"datatype":"news","pubDate":"2026-06-18 07:55:37","pubDateTZ":"UTC","fetched_at":"2026-06-18 08:02:46","image_url":null,"video_url":null,"source_id":"investing_il","source_name":"Investing","source_priority":1143,"source_url":"https://il.investing.com","source_icon":"https://n.bytvi.com/investing_il.png","sentiment":"ONLY AVAILABLE IN PROFESSIONAL AND CORPORATE PLANS","sentiment_stats":"ONLY AVAILABLE IN PROFESSIONAL AND CORPORATE PLANS","ai_tag":"ONLY AVAILABLE IN PROFESSIONAL AND CORPORATE PLANS","ai_region":"ONLY AVAILABLE IN CORPORATE PLANS","ai_org":"ONLY AVAILABLE IN CORPORATE PLANS","ai_summary":"ONLY AVAILABLE IN PAID PLANS","duplicate":false},{"article_id":"15426fdb7ad922b53574fc12c61b4f99","link":"https://www.israelhayom.co.il/sport/israeli-soccer/article/20788997","title":"שחקן בית\"ר ירושלים סיכם בקבוצה חדשה | פרסום ראשון","description":"עילאי חג'ג' סיכם את תנאיו בעולה החדשה לליגה הלאומית, מ.ס קריית גת, וצפוי לצאת להשאלה נוספת אחרי המעבר ממכבי חיפה","content":"ONLY AVAILABLE IN PAID PLANS","keywords":["בית\"ר ירושלים","מכבי חיפה"],"creator":["אבי אוחיון"],"language":"hebrew","country":["israel"],"category":["sports","top"],"datatype":"news","pubDate":"2026-06-18 07:55:29","pubDateTZ":"UTC","fetched_at":"2026-06-18 08:03:26","image_url":"https://www.israelhayom.co.il/wp-content/uploads/2026/01/25/25/New_024A9617.jpg","video_url":null,"source_id":"israelhayom","source_name":"ישראל היום","source_priority":13660,"source_url":"https://www.israelhayom.co.il","source_icon":"https://n.bytvi.com/israelhayom.jpg","sentiment":"ONLY AVAILABLE IN PROFESSIONAL AND CORPORATE PLANS","sentiment_stats":"ONLY AVAILABLE IN PROFESSIONAL AND CORPORATE PLANS","ai_tag":"ONLY AVAILABLE IN PROFESSIONAL AND CORPORATE PLANS","ai_region":"ONLY AVAILABLE IN CORPORATE PLANS","ai_org":"ONLY AVAILABLE IN CORPORATE PLANS","ai_summary":"ONLY AVAILABLE IN PAID PLANS","duplicate":false},{"article_id":"54ee1ee5234d121e4bbc3c62e92f45a0","link":"https://www.israelhayom.co.il/business/article/20788933","title":"שבוע אדום בבורסה: הכסף החדש זורם לארה\"ב על חשבון השוק הישראלי","description":"העליות מתחילת השנה נמחקו, והכלכלנים מזהירים מפני תקופה ממושכת של צמיחה חלשה • לצד הציפייה להורדת ריבית, ההערכות הן שהגידול בהוצאות הביטחון יכביד על המשק בשנים הקרובות","content":"ONLY AVAILABLE IN PAID PLANS","keywords":["מיסים","דולר","בורסה"],"creator":["ניצן כהן"],"language":"hebrew","country":["israel"],"category":["business","top"],"datatype":"news","pubDate":"2026-06-18 07:54:43","pubDateTZ":"UTC","fetched_at":"2026-06-18 08:03:26","image_url":"https://www.israelhayom.co.il/wp-content/uploads/2026/03/16/16/44A7942.jpg","video_url":null,"source_id":"israelhayom","source_name":"ישראל היום","source_priority":13660,"source_url":"https://www.israelhayom.co.il","source_icon":"https://n.bytvi.com/israelhayom.jpg","sentiment":"ONLY AVAILABLE IN PROFESSIONAL AND CORPORATE PLANS","sentiment_stats":"ONLY AVAILABLE IN PROFESSIONAL AND CORPORATE PLANS","ai_tag":"ONLY AVAILABLE IN PROFESSIONAL AND CORPORATE PLANS","ai_region":"ONLY AVAILABLE IN CORPORATE PLANS","ai_org":"ONLY AVAILABLE IN CORPORATE PLANS","ai_summary":"ONLY AVAILABLE IN PAID PLANS","duplicate":false},{"article_id":"5dd31e0f1ab2a7206d61ac17fe8c3fa7","link":"https://www.israelhayom.co.il/news/crime/article/20788938","title":"\"אכזרי ואלים במיוחד\": מאסר עולם לרוצח סיגלית אטיאס בלוד","description":"בית המשפט המחוזי מרכז גזר את עונשו של משה אטיאס, שרצח את אשתו באמצעות משקולת כבדה ודקירות סכין, הכין לעצמו קפה והתקשר למד\"א • לימור, אחותה של הנרצחת: \"הרוצח ניסה להתחמק מאחריות למעשיו, מקווה שלא יראה יותר אור יום בחייו\"","content":"ONLY AVAILABLE IN PAID PLANS","keywords":["רצח"],"creator":["אבי כהן"],"language":"hebrew","country":["israel"],"category":["crime","top"],"datatype":"news","pubDate":"2026-06-18 07:52:07","pubDateTZ":"UTC","fetched_at":"2026-06-18 08:03:26","image_url":"https://www.israelhayom.co.il/wp-content/uploads/2023/03/06/06/%D7%A8%D7%A9%D7%AA%D7%95%D7%AA-%D7%97%D7%91%D7%A8%D7%AA%D7%99%D7%95%D7%AA-%D7%A0%D7%A8%D7%A6%D7%97%D7%AA.jpg","video_url":null,"source_id":"israelhayom","source_name":"ישראל היום","source_priority":13660,"source_url":"https://www.israelhayom.co.il","source_icon":"https://n.bytvi.com/israelhayom.jpg","sentiment":"ONLY AVAILABLE IN PROFESSIONAL AND CORPORATE PLANS","sentiment_stats":"ONLY AVAILABLE IN PROFESSIONAL AND CORPORATE PLANS","ai_tag":"ONLY AVAILABLE IN PROFESSIONAL AND CORPORATE PLANS","ai_region":"ONLY AVAILABLE IN CORPORATE PLANS","ai_org":"ONLY AVAILABLE IN CORPORATE PLANS","ai_summary":"ONLY AVAILABLE IN PAID PLANS","duplicate":false},{"article_id":"f8648e8546744e4aa00bfbf6a8b55057","link":"https://il.investing.com/news/earnings/article-882676","title":"מניות FirstGroup קופצות ב-6% על רקע רווחים מעל התחזיות ותוכנית רכישה של £100 מיליון","description":null,"content":"ONLY AVAILABLE IN PAID PLANS","keywords":null,"creator":null,"language":"hebrew","country":["israel"],"category":["business","top"],"datatype":"news","pubDate":"2026-06-18 07:51:38","pubDateTZ":"UTC","fetched_at":"2026-06-18 08:02:46","image_url":null,"video_url":null,"source_id":"investing_il","source_name":"Investing","source_priority":1143,"source_url":"https://il.investing.com","source_icon":"https://n.bytvi.com/investing_il.png","sentiment":"ONLY AVAILABLE IN PROFESSIONAL AND CORPORATE PLANS","sentiment_stats":"ONLY AVAILABLE IN PROFESSIONAL AND CORPORATE PLANS","ai_tag":"ONLY AVAILABLE IN PROFESSIONAL AND CORPORATE PLANS","ai_region":"ONLY AVAILABLE IN CORPORATE PLANS","ai_org":"ONLY AVAILABLE IN CORPORATE PLANS","ai_summary":"ONLY AVAILABLE IN PAID PLANS","duplicate":false}],"nextPage":"1781769098861878850"}
