{"status":"success","totalResults":2126,"results":[{"article_id":"750f4ffca2f2a378b94417ca184c0fa4","link":"https://il.investing.com/news/insider-trading-news/article-93CH-715557","title":"דורצ’סטר מינרלס אופרייטינג LP רוכשת יחידות DMLP בשווי 334 אלף דולר","description":null,"content":"ONLY AVAILABLE IN PAID PLANS","keywords":null,"creator":["investing.com"],"language":"hebrew","country":["israel"],"category":["business","top"],"datatype":"news","pubDate":"2025-12-23 16:20:04","pubDateTZ":"UTC","fetched_at":"2025-12-23 16:36:32","image_url":"https://i-invdn-com.investing.com/news/world_news_2_108x81.jpg","video_url":null,"source_id":"investing_il","source_name":"Investing","source_priority":1143,"source_url":"https://il.investing.com","source_icon":"https://n.bytvi.com/investing_il.png","sentiment":"ONLY AVAILABLE IN PROFESSIONAL AND CORPORATE PLANS","sentiment_stats":"ONLY AVAILABLE IN PROFESSIONAL AND CORPORATE PLANS","ai_tag":"ONLY AVAILABLE IN PROFESSIONAL AND CORPORATE PLANS","ai_region":"ONLY AVAILABLE IN CORPORATE PLANS","ai_org":"ONLY AVAILABLE IN CORPORATE PLANS","ai_summary":"ONLY AVAILABLE IN PAID PLANS","duplicate":false},{"article_id":"773b69d663a148887df2c25be1cc398d","link":"https://il.investing.com/news/insider-trading-news/article-93CH-715556","title":"ינאביץ’ ויליאם ט. השני רוכש מניות יורק ווטר בשווי 1,499 דולר","description":null,"content":"ONLY AVAILABLE IN PAID PLANS","keywords":null,"creator":["investing.com"],"language":"hebrew","country":["israel"],"category":["business","top"],"datatype":"news","pubDate":"2025-12-23 16:20:02","pubDateTZ":"UTC","fetched_at":"2025-12-23 16:36:32","image_url":"https://i-invdn-com.investing.com/news/world_news_2_108x81.jpg","video_url":null,"source_id":"investing_il","source_name":"Investing","source_priority":1143,"source_url":"https://il.investing.com","source_icon":"https://n.bytvi.com/investing_il.png","sentiment":"ONLY AVAILABLE IN PROFESSIONAL AND CORPORATE PLANS","sentiment_stats":"ONLY AVAILABLE IN PROFESSIONAL AND CORPORATE PLANS","ai_tag":"ONLY AVAILABLE IN PROFESSIONAL AND CORPORATE PLANS","ai_region":"ONLY AVAILABLE IN CORPORATE PLANS","ai_org":"ONLY AVAILABLE IN CORPORATE PLANS","ai_summary":"ONLY AVAILABLE IN PAID PLANS","duplicate":false},{"article_id":"db96b4e4d08e61fd2c7aed7f5063b94d","link":"https://www.inn.co.il/news/686065","title":"דיווח בלבנון: קצין בצבא נחטף בשל קשר לחטיפת רון ארד","description":"קצין הביטחון הלבנוני לשעבר, אחמד שוכר, נעלם באזור הבקעא. גורמים לבנוניים טוענים כי ייתכן שנחטף על ידי ישראל במבצע מודיעיני","content":"ONLY AVAILABLE IN PAID PLANS","keywords":null,"creator":null,"language":"hebrew","country":["israel"],"category":["lifestyle","top"],"datatype":"news","pubDate":"2025-12-23 16:20:00","pubDateTZ":"UTC","fetched_at":"2025-12-23 16:49:13","image_url":"https://2.a7.org/files/pictures/781x439/1110748.jpg","video_url":null,"source_id":"inn","source_name":"Inn","source_priority":129730,"source_url":"https://www.inn.co.il","source_icon":"https://n.bytvi.com/inn.png","sentiment":"ONLY AVAILABLE IN PROFESSIONAL AND CORPORATE PLANS","sentiment_stats":"ONLY AVAILABLE IN PROFESSIONAL AND CORPORATE PLANS","ai_tag":"ONLY AVAILABLE IN PROFESSIONAL AND CORPORATE PLANS","ai_region":"ONLY AVAILABLE IN CORPORATE PLANS","ai_org":"ONLY AVAILABLE IN CORPORATE PLANS","ai_summary":"ONLY AVAILABLE IN PAID PLANS","duplicate":false},{"article_id":"01036b21792fd460d57b73e8ca022bf8","link":"https://il.investing.com/news/stock-market-news/article-93CH-715555","title":"מניית סילינקסקום זינקה לאחר הבטחת הזמנות בשווי 1.3 מיליון דולר מארגוני הביטחון הישראליים","description":null,"content":"ONLY AVAILABLE IN PAID PLANS","keywords":null,"creator":["investing.com"],"language":"hebrew","country":["israel"],"category":["lifestyle","top"],"datatype":"news","pubDate":"2025-12-23 16:14:46","pubDateTZ":"UTC","fetched_at":"2025-12-23 16:36:30","image_url":"https://i-invdn-com.investing.com/news/world_news_2_108x81.jpg","video_url":null,"source_id":"investing_il","source_name":"Investing","source_priority":1143,"source_url":"https://il.investing.com","source_icon":"https://n.bytvi.com/investing_il.png","sentiment":"ONLY AVAILABLE IN PROFESSIONAL AND CORPORATE PLANS","sentiment_stats":"ONLY AVAILABLE IN PROFESSIONAL AND CORPORATE PLANS","ai_tag":"ONLY AVAILABLE IN PROFESSIONAL AND CORPORATE PLANS","ai_region":"ONLY AVAILABLE IN CORPORATE PLANS","ai_org":"ONLY AVAILABLE IN CORPORATE PLANS","ai_summary":"ONLY AVAILABLE IN PAID PLANS","duplicate":false},{"article_id":"a8d2b30c0ea2dba3f6c4368fd2c0b4da","link":"https://www.maariv.co.il/news/israel/article-1265373","title":"בשורה קשה לנהגים בעיר העמוסה - הפקקים יהפכו לחמורים עוד יותר","description":"היכונו לעומסי תנועה כבדים במרכז ראשון לציון. החל מהלילה ייפרס הסדר תנועה חדש ברחוב מרכזי בעיר, במסגרת המשך העבודות להקמת מטרונית הקו החום – מערכת הסעת המונים באמצעות מטרונית","content":"ONLY AVAILABLE IN PAID PLANS","keywords":["מטרו","עבודות בכביש","מטרונית","ראשון לציון","הרכבת הקלה"],"creator":null,"language":"hebrew","country":["israel"],"category":["lifestyle","top"],"datatype":"news","pubDate":"2025-12-23 16:14:25","pubDateTZ":"UTC","fetched_at":"2025-12-23 16:45:36","image_url":"https://images.maariv.co.il/image/upload/f_auto,fl_lossy/c_fill,g_faces:center,w_1200/825519","video_url":null,"source_id":"maariv","source_name":"מעריב","source_priority":43057,"source_url":"https://www.maariv.co.il","source_icon":"https://n.bytvi.com/maariv.png","sentiment":"ONLY AVAILABLE IN PROFESSIONAL AND CORPORATE PLANS","sentiment_stats":"ONLY AVAILABLE IN PROFESSIONAL AND CORPORATE PLANS","ai_tag":"ONLY AVAILABLE IN PROFESSIONAL AND CORPORATE PLANS","ai_region":"ONLY AVAILABLE IN CORPORATE PLANS","ai_org":"ONLY AVAILABLE IN CORPORATE PLANS","ai_summary":"ONLY AVAILABLE IN PAID PLANS","duplicate":false},{"article_id":"9f3cc254e1844c805b1fca034cb91994","link":"https://il.investing.com/news/company-news/article-93CH-715554","title":"ג’יי פי מורגן צ’ייס מגדילה אחזקתה ב-PRS REIT למעל 9%","description":null,"content":"ONLY AVAILABLE IN PAID PLANS","keywords":null,"creator":["investing.com"],"language":"hebrew","country":["israel"],"category":["business","top"],"datatype":"news","pubDate":"2025-12-23 16:14:23","pubDateTZ":"UTC","fetched_at":"2025-12-23 16:36:32","image_url":"https://i-invdn-com.investing.com/news/world_news_2_108x81.jpg","video_url":null,"source_id":"investing_il","source_name":"Investing","source_priority":1143,"source_url":"https://il.investing.com","source_icon":"https://n.bytvi.com/investing_il.png","sentiment":"ONLY AVAILABLE IN PROFESSIONAL AND CORPORATE PLANS","sentiment_stats":"ONLY AVAILABLE IN PROFESSIONAL AND CORPORATE PLANS","ai_tag":"ONLY AVAILABLE IN PROFESSIONAL AND CORPORATE PLANS","ai_region":"ONLY AVAILABLE IN CORPORATE PLANS","ai_org":"ONLY AVAILABLE IN CORPORATE PLANS","ai_summary":"ONLY AVAILABLE IN PAID PLANS","duplicate":false},{"article_id":"97066940504909d1399aa7ef8c1773d6","link":"https://news.walla.co.il/item/3803621","title":"\"חטיפה צריכה להיות נטל על האויב - לא נכס\": יוזמת החקיקה החדשה","description":"חבר הכנסת אוהד טל מקדם הצעת חוק לעיגון מסקנות ועדת שמגר: \"עלינו לעמוד מול טרור החטיפות ולומר - עד כאן!\". בכנס שנערך בשיתוף מכון יכין השתתפו שרים, חברי כנסת ומשפחות שכולות שדרשו שינוי אסטרטגי במדיניות פדיון השבויים","content":"ONLY AVAILABLE IN PAID PLANS","keywords":null,"creator":["אבי סולומון"],"language":"hebrew","country":["israel"],"category":["lifestyle","top"],"datatype":"news","pubDate":"2025-12-23 16:13:14","pubDateTZ":"UTC","fetched_at":"2025-12-23 16:13:14","image_url":"https://images.wcdn.co.il/f_auto,q_auto,w_300/3/9/9/0/3990609-46.jpeg","video_url":null,"source_id":"walla","source_name":"Walla!","source_priority":26977,"source_url":"https://www.walla.co.il","source_icon":"https://n.bytvi.com/walla.png","sentiment":"ONLY AVAILABLE IN PROFESSIONAL AND CORPORATE PLANS","sentiment_stats":"ONLY AVAILABLE IN PROFESSIONAL AND CORPORATE PLANS","ai_tag":"ONLY AVAILABLE IN PROFESSIONAL AND CORPORATE PLANS","ai_region":"ONLY AVAILABLE IN CORPORATE PLANS","ai_org":"ONLY AVAILABLE IN CORPORATE PLANS","ai_summary":"ONLY AVAILABLE IN PAID PLANS","duplicate":false},{"article_id":"ea9dd254f54bcb048cddb1cc5f5a014a","link":"https://www.israelhayom.co.il/sport/israeli-soccer/article/19524159","title":"במכבי נתניה מצאו את בלם העתיד: \"משווים אותו למתן בלטקסה\"","description":"בני פלדמן, שחקן ההגנה הצעיר של היהלומים, כבר בלט נגד מכבי חיפה וצפוי להיות גורם משמעותי כבר בעונה הבאה • בקבוצה שיתפו: \"נמאס לנו להשקיע בבלמים זרים\" • מאמנו בקבוצת הנוער, סשה פלדמן, סיפר: \"מדובר באישיות בלתי רגילה\"","content":"ONLY AVAILABLE IN PAID PLANS","keywords":["כדורגל ישראלי"],"creator":["מיכאל וייסרמן"],"language":"hebrew","country":["israel"],"category":["lifestyle","top"],"datatype":"news","pubDate":"2025-12-23 16:10:23","pubDateTZ":"UTC","fetched_at":"2025-12-23 16:10:23","image_url":"https://www.israelhayom.co.il/wp-content/uploads/2025/12/23/23/New_BER_3071-13-2.jpg","video_url":null,"source_id":"israelhayom","source_name":"ישראל היום","source_priority":13660,"source_url":"https://www.israelhayom.co.il","source_icon":"https://n.bytvi.com/israelhayom.jpg","sentiment":"ONLY AVAILABLE IN PROFESSIONAL AND CORPORATE PLANS","sentiment_stats":"ONLY AVAILABLE IN PROFESSIONAL AND CORPORATE PLANS","ai_tag":"ONLY AVAILABLE IN PROFESSIONAL AND CORPORATE PLANS","ai_region":"ONLY AVAILABLE IN CORPORATE PLANS","ai_org":"ONLY AVAILABLE IN CORPORATE PLANS","ai_summary":"ONLY AVAILABLE IN PAID PLANS","duplicate":false},{"article_id":"eb2ec8d17415797fe3bc7d4188d37746","link":"https://www.israelhayom.co.il/news/local/article/19524127","title":"\"להתאחד ולהלחם ברוע\": הביקור של המשלחת המוסלמית בעוטף עזה","description":"עשרות אנשי דת מוסלמים סיירו באתר הנובה, בקיבוץ נחל עוז ובנקודות ציון נוספות של טבח 7.10 • אימראן עטא-איגרה מארה\"ב: \"אל תאמינו למה שהתקשורת הבינלאומית או הצד השני מספרים לכם - בואו לראות במו עיניכם, שכן הכול כאן חשוף וגלוי\"","content":"ONLY AVAILABLE IN PAID PLANS","keywords":["בארץ"],"creator":["מור שפייר"],"language":"hebrew","country":["israel"],"category":["top"],"datatype":"news","pubDate":"2025-12-23 16:10:23","pubDateTZ":"UTC","fetched_at":"2025-12-23 16:10:23","image_url":"https://www.israelhayom.co.il/wp-content/uploads/2025/12/23/23/WhatsApp-Image-2025-12-23-at-16.27.17-1.jpeg","video_url":null,"source_id":"israelhayom","source_name":"ישראל היום","source_priority":13660,"source_url":"https://www.israelhayom.co.il","source_icon":"https://n.bytvi.com/israelhayom.jpg","sentiment":"ONLY AVAILABLE IN PROFESSIONAL AND CORPORATE PLANS","sentiment_stats":"ONLY AVAILABLE IN PROFESSIONAL AND CORPORATE PLANS","ai_tag":"ONLY AVAILABLE IN PROFESSIONAL AND CORPORATE PLANS","ai_region":"ONLY AVAILABLE IN CORPORATE PLANS","ai_org":"ONLY AVAILABLE IN CORPORATE PLANS","ai_summary":"ONLY AVAILABLE IN PAID PLANS","duplicate":false},{"article_id":"46fab2154ec29a57f3a8f4c4c35adf56","link":"https://www.israelhayom.co.il/tech/research/article/19524024","title":"הסוף לכדורים? חוקרים ישראלים מצאו דרך לפתח תרופות בתוך הגוף","description":"במסגרת מחקר של הטכניון נבדקה מדבקה המחדירה לעור חיידקים לא מזיקים שמייצרים חומרים תרופתיים ישירות באיבר החולה • הטכנולוגיה עשויה לצמצם את הצורך בבליעת תרופות יומיומית, לשפר את יעילות הטיפול ולהפחית תופעות לוואי","content":"ONLY AVAILABLE IN PAID PLANS","keywords":["מחקרים"],"creator":["אסף גולן"],"language":"hebrew","country":["israel"],"category":["top"],"datatype":"news","pubDate":"2025-12-23 16:10:22","pubDateTZ":"UTC","fetched_at":"2025-12-23 16:10:22","image_url":"https://www.israelhayom.co.il/wp-content/uploads/2025/12/23/23/Generated-image-1.png","video_url":null,"source_id":"israelhayom","source_name":"ישראל היום","source_priority":13660,"source_url":"https://www.israelhayom.co.il","source_icon":"https://n.bytvi.com/israelhayom.jpg","sentiment":"ONLY AVAILABLE IN PROFESSIONAL AND CORPORATE PLANS","sentiment_stats":"ONLY AVAILABLE IN PROFESSIONAL AND CORPORATE PLANS","ai_tag":"ONLY AVAILABLE IN PROFESSIONAL AND CORPORATE PLANS","ai_region":"ONLY AVAILABLE IN CORPORATE PLANS","ai_org":"ONLY AVAILABLE IN CORPORATE PLANS","ai_summary":"ONLY AVAILABLE IN PAID PLANS","duplicate":false}],"nextPage":"1766506222734283137"}
