{"status":"success","totalResults":1723,"results":[{"article_id":"f707ba9ae231e640908b0908e26e50a1","title":"תמלול שיחת רווחים: הרבעון הראשון של 2025 של ליונטאון משקף ירידה בהכנסות, המניה צונחת","link":"https://il.investing.com/news/transcripts/article-93CH-661397","keywords":null,"creator":["Investing.com"],"description":null,"content":"ONLY AVAILABLE IN PAID PLANS","pubDate":"2025-10-28 01:54:47","pubDateTZ":"UTC","image_url":"https://i-invdn-com.investing.com/news/international_newspapers_108x81.jpg","video_url":null,"source_id":"investing_il","source_name":"Investing","source_priority":1143,"source_url":"https://il.investing.com","source_icon":null,"language":"hebrew","country":["israel"],"category":["lifestyle","top"],"sentiment":"ONLY AVAILABLE IN PROFESSIONAL AND CORPORATE PLANS","sentiment_stats":"ONLY AVAILABLE IN PROFESSIONAL AND CORPORATE PLANS","ai_tag":"ONLY AVAILABLE IN PROFESSIONAL AND CORPORATE PLANS","ai_region":"ONLY AVAILABLE IN CORPORATE PLANS","ai_org":"ONLY AVAILABLE IN CORPORATE PLANS","ai_summary":"ONLY AVAILABLE IN PAID PLANS","ai_content":"ONLY AVAILABLE IN PROFESSIONAL AND CORPORATE PLANS","duplicate":false},{"article_id":"abde05a43cfe98ea58a462531d303b43","title":"מחירי הנפט יציבים עם מיקוד במתחים בין ארה\"ב לסין והגדלת תפוקת אופ\"ק","link":"https://il.investing.com/news/commodities-news/article-661398","keywords":null,"creator":["Investing.com"],"description":null,"content":"ONLY AVAILABLE IN PAID PLANS","pubDate":"2025-10-28 01:54:13","pubDateTZ":"UTC","image_url":"https://i-invdn-com.investing.com/news/LYNXMPEE5S1ZM_M.jpg","video_url":null,"source_id":"investing_il","source_name":"Investing","source_priority":1143,"source_url":"https://il.investing.com","source_icon":null,"language":"hebrew","country":["israel"],"category":["lifestyle","top"],"sentiment":"ONLY AVAILABLE IN PROFESSIONAL AND CORPORATE PLANS","sentiment_stats":"ONLY AVAILABLE IN PROFESSIONAL AND CORPORATE PLANS","ai_tag":"ONLY AVAILABLE IN PROFESSIONAL AND CORPORATE PLANS","ai_region":"ONLY AVAILABLE IN CORPORATE PLANS","ai_org":"ONLY AVAILABLE IN CORPORATE PLANS","ai_summary":"ONLY AVAILABLE IN PAID PLANS","ai_content":"ONLY AVAILABLE IN PROFESSIONAL AND CORPORATE PLANS","duplicate":false},{"article_id":"1c7efb7dfc026fe8722d0110f44af870","title":"בארי קיט רוכש מניות Quest Resource (QRHC) בשווי 260,592 דולר","link":"https://il.investing.com/news/insider-trading-news/article-93CH-661395","keywords":null,"creator":["Investing.com"],"description":null,"content":"ONLY AVAILABLE IN PAID PLANS","pubDate":"2025-10-28 01:53:26","pubDateTZ":"UTC","image_url":"https://i-invdn-com.investing.com/news/news_headline_rolled_108x81.jpg","video_url":null,"source_id":"investing_il","source_name":"Investing","source_priority":1143,"source_url":"https://il.investing.com","source_icon":null,"language":"hebrew","country":["israel"],"category":["business","top"],"sentiment":"ONLY AVAILABLE IN PROFESSIONAL AND CORPORATE PLANS","sentiment_stats":"ONLY AVAILABLE IN PROFESSIONAL AND CORPORATE PLANS","ai_tag":"ONLY AVAILABLE IN PROFESSIONAL AND CORPORATE PLANS","ai_region":"ONLY AVAILABLE IN CORPORATE PLANS","ai_org":"ONLY AVAILABLE IN CORPORATE PLANS","ai_summary":"ONLY AVAILABLE IN PAID PLANS","ai_content":"ONLY AVAILABLE IN PROFESSIONAL AND CORPORATE PLANS","duplicate":false},{"article_id":"1068f1c69383fb46ae1a656013622963","title":"מנכ\"ל Rise Gold מאלין רוכש מניות בחברה בשווי 20,000 דולר","link":"https://il.investing.com/news/insider-trading-news/article-93CH-661393","keywords":null,"creator":["Investing.com"],"description":null,"content":"ONLY AVAILABLE IN PAID PLANS","pubDate":"2025-10-28 01:42:34","pubDateTZ":"UTC","image_url":"https://i-invdn-com.investing.com/news/news_headline_rolled_108x81.jpg","video_url":null,"source_id":"investing_il","source_name":"Investing","source_priority":1143,"source_url":"https://il.investing.com","source_icon":null,"language":"hebrew","country":["israel"],"category":["business","top"],"sentiment":"ONLY AVAILABLE IN PROFESSIONAL AND CORPORATE PLANS","sentiment_stats":"ONLY AVAILABLE IN PROFESSIONAL AND CORPORATE PLANS","ai_tag":"ONLY AVAILABLE IN PROFESSIONAL AND CORPORATE PLANS","ai_region":"ONLY AVAILABLE IN CORPORATE PLANS","ai_org":"ONLY AVAILABLE IN CORPORATE PLANS","ai_summary":"ONLY AVAILABLE IN PAID PLANS","ai_content":"ONLY AVAILABLE IN PROFESSIONAL AND CORPORATE PLANS","duplicate":false},{"article_id":"df3f86df020ca91f9c03859ff6460f25","title":"פוני AI משיקה הנפקה ראשונה לציבור בהונג קונג; מתכננת להרחיב מו\"פ מהתקבולים","link":"https://il.investing.com/news/stock-market-news/article-661392","keywords":null,"creator":["Investing.com"],"description":null,"content":"ONLY AVAILABLE IN PAID PLANS","pubDate":"2025-10-28 01:39:09","pubDateTZ":"UTC","image_url":null,"video_url":null,"source_id":"investing_il","source_name":"Investing","source_priority":1143,"source_url":"https://il.investing.com","source_icon":null,"language":"hebrew","country":["israel"],"category":["lifestyle","top"],"sentiment":"ONLY AVAILABLE IN PROFESSIONAL AND CORPORATE PLANS","sentiment_stats":"ONLY AVAILABLE IN PROFESSIONAL AND CORPORATE PLANS","ai_tag":"ONLY AVAILABLE IN PROFESSIONAL AND CORPORATE PLANS","ai_region":"ONLY AVAILABLE IN CORPORATE PLANS","ai_org":"ONLY AVAILABLE IN CORPORATE PLANS","ai_summary":"ONLY AVAILABLE IN PAID PLANS","ai_content":"ONLY AVAILABLE IN PROFESSIONAL AND CORPORATE PLANS","duplicate":false},{"article_id":"51b5b59c8b41762398b451952dea8ec9","title":"דירקטור דלק US הולדינגס ימין מוכר מניות סטוק בשווי 5 מיליון דולר","link":"https://il.investing.com/news/insider-trading-news/article-93CH-661391","keywords":null,"creator":["Investing.com"],"description":null,"content":"ONLY AVAILABLE IN PAID PLANS","pubDate":"2025-10-28 01:36:29","pubDateTZ":"UTC","image_url":null,"video_url":null,"source_id":"investing_il","source_name":"Investing","source_priority":1143,"source_url":"https://il.investing.com","source_icon":null,"language":"hebrew","country":["israel"],"category":["lifestyle","top"],"sentiment":"ONLY AVAILABLE IN PROFESSIONAL AND CORPORATE PLANS","sentiment_stats":"ONLY AVAILABLE IN PROFESSIONAL AND CORPORATE PLANS","ai_tag":"ONLY AVAILABLE IN PROFESSIONAL AND CORPORATE PLANS","ai_region":"ONLY AVAILABLE IN CORPORATE PLANS","ai_org":"ONLY AVAILABLE IN CORPORATE PLANS","ai_summary":"ONLY AVAILABLE IN PAID PLANS","ai_content":"ONLY AVAILABLE IN PROFESSIONAL AND CORPORATE PLANS","duplicate":false},{"article_id":"0562b1d9d55a4c57944e2b28b4812226","title":"קפלן מירון רוכש מניות CorMedix בשווי 275 אלף דולר","link":"https://il.investing.com/news/insider-trading-news/article-93CH-661390","keywords":null,"creator":["Investing.com"],"description":null,"content":"ONLY AVAILABLE IN PAID PLANS","pubDate":"2025-10-28 01:36:28","pubDateTZ":"UTC","image_url":"https://i-invdn-com.investing.com/news/World_News_8_M_1440052125.jpg","video_url":null,"source_id":"investing_il","source_name":"Investing","source_priority":1143,"source_url":"https://il.investing.com","source_icon":null,"language":"hebrew","country":["israel"],"category":["business","top"],"sentiment":"ONLY AVAILABLE IN PROFESSIONAL AND CORPORATE PLANS","sentiment_stats":"ONLY AVAILABLE IN PROFESSIONAL AND CORPORATE PLANS","ai_tag":"ONLY AVAILABLE IN PROFESSIONAL AND CORPORATE PLANS","ai_region":"ONLY AVAILABLE IN CORPORATE PLANS","ai_org":"ONLY AVAILABLE IN CORPORATE PLANS","ai_summary":"ONLY AVAILABLE IN PAID PLANS","ai_content":"ONLY AVAILABLE IN PROFESSIONAL AND CORPORATE PLANS","duplicate":false},{"article_id":"cccfa690b05aac3de959db0cffd924ca","title":"ארה\"ב - MLS - פלייאוף: מינסוטה יונייטד - סיאטל סאונדרס","link":"https://www.israelhayom.co.il/sport/article/19115682","keywords":["ספורט"],"creator":["מערכת ספורט היום"],"description":null,"content":"ONLY AVAILABLE IN PAID PLANS","pubDate":"2025-10-28 01:34:49","pubDateTZ":"UTC","image_url":null,"video_url":null,"source_id":"israelhayom","source_name":"ישראל היום","source_priority":13660,"source_url":"https://www.israelhayom.co.il","source_icon":null,"language":"hebrew","country":["israel"],"category":["lifestyle","top"],"sentiment":"ONLY AVAILABLE IN PROFESSIONAL AND CORPORATE PLANS","sentiment_stats":"ONLY AVAILABLE IN PROFESSIONAL AND CORPORATE PLANS","ai_tag":"ONLY AVAILABLE IN PROFESSIONAL AND CORPORATE PLANS","ai_region":"ONLY AVAILABLE IN CORPORATE PLANS","ai_org":"ONLY AVAILABLE IN CORPORATE PLANS","ai_summary":"ONLY AVAILABLE IN PAID PLANS","ai_content":"ONLY AVAILABLE IN PROFESSIONAL AND CORPORATE PLANS","duplicate":false},{"article_id":"63cdf988a187d734a26766d876e0c320","title":"בשידור ישיר: אופנוען התרסק במהלך מרדף מטורף במהירות גבוהה לאחר שירה בשוטר","link":"https://www.israelhayom.co.il/news/world-news/usa/article/19115674","keywords":["ארצות הברית"],"creator":["מערכת ישראל היום"],"description":"שוטרים שהוזעקו לאירוע אלימות משפחתית נורו ואחד מהם נרצח • החשוד ברצח נמלט על אופנוע במהירות שהגיעה ל-320 קמ\"ש • התפנית הגיעה לאחר ששוטר שלא היה בתפקיד ונסע ברכבו האזרחי החליט להצטרף למרדף","content":"ONLY AVAILABLE IN PAID PLANS","pubDate":"2025-10-28 01:34:48","pubDateTZ":"UTC","image_url":"https://www.israelhayom.co.il/wp-content/uploads/2025/10/28/28/Capture6.png","video_url":null,"source_id":"israelhayom","source_name":"ישראל היום","source_priority":13660,"source_url":"https://www.israelhayom.co.il","source_icon":null,"language":"hebrew","country":["israel"],"category":["lifestyle","top"],"sentiment":"ONLY AVAILABLE IN PROFESSIONAL AND CORPORATE PLANS","sentiment_stats":"ONLY AVAILABLE IN PROFESSIONAL AND CORPORATE PLANS","ai_tag":"ONLY AVAILABLE IN PROFESSIONAL AND CORPORATE PLANS","ai_region":"ONLY AVAILABLE IN CORPORATE PLANS","ai_org":"ONLY AVAILABLE IN CORPORATE PLANS","ai_summary":"ONLY AVAILABLE IN PAID PLANS","ai_content":"ONLY AVAILABLE IN PROFESSIONAL AND CORPORATE PLANS","duplicate":false},{"article_id":"43e1188ac80207fad64486691a6b1aea","title":"הסופה החזקה ב-174 שנה תפגע בג'מייקה, רה״מ: \"התפללתי על ברכיי\" | תיעוד הסערה","link":"https://www.israelhayom.co.il/news/world-news/article/19115654","keywords":["העולם"],"creator":["אי.פי"],"description":"הוריקן מליסה התחזק לדרגה 5 - העליונה בסיווג ההוריקנים, וצפוי לפגוע היום בג׳מייקה עם רוחות של 280 קמ״ש • הסופה כבר גרמה למותם של שישה אנשים בצפון הקריביים והיא צפויה להביא שיטפונות קטסטרופליים ומפולות • צווי פינוי הוצאו לאזורים מוצפים, אך רבים מהתושבים מסרבים לעזוב את בתיהם: \"לא הולך לשום מקום\" • זו תהיה הסופה החזקה ביותר שפגעה באי מאז שהחלו התצפיות ב-1851","content":"ONLY AVAILABLE IN PAID PLANS","pubDate":"2025-10-28 01:34:48","pubDateTZ":"UTC","image_url":"https://www.israelhayom.co.il/wp-content/uploads/2025/10/28/28/Jamaica_Extreme_Weather_55989-f44e1.jpg","video_url":null,"source_id":"israelhayom","source_name":"ישראל היום","source_priority":13660,"source_url":"https://www.israelhayom.co.il","source_icon":null,"language":"hebrew","country":["israel"],"category":["lifestyle","top"],"sentiment":"ONLY AVAILABLE IN PROFESSIONAL AND CORPORATE PLANS","sentiment_stats":"ONLY AVAILABLE IN PROFESSIONAL AND CORPORATE PLANS","ai_tag":"ONLY AVAILABLE IN PROFESSIONAL AND CORPORATE PLANS","ai_region":"ONLY AVAILABLE IN CORPORATE PLANS","ai_org":"ONLY AVAILABLE IN CORPORATE PLANS","ai_summary":"ONLY AVAILABLE IN PAID PLANS","ai_content":"ONLY AVAILABLE IN PROFESSIONAL AND CORPORATE PLANS","duplicate":false}],"nextPage":"1761615288029644499"}
