{"status":"success","totalResults":2166,"results":[{"article_id":"9b06db214d2d9bbf28fca741d3c4c27e","title":"קרלו אנצ'לוטי הורשע בהעלמת מס ונידון לשנת מאסר, אבל לא צפוי לרצות את העונש","link":"https://www.haaretz.co.il/sport/world-soccer/2025-07-09/ty-article/00000197-ef99-de26-a1ff-ffdba1bb0000","keywords":null,"creator":["ספורט הארץ"],"description":"מאמן נבחרת ברזיל הורשע בהעלמת מס של יותר ממיליון יורו בשנים 2014 ו-2015, בהן אימן את ריאל מדריד. בספרד נהוג להמיר עונשי מאסר של מתחת לשנה בעבודות שירות או קנסות","content":"ONLY AVAILABLE IN PAID PLANS","pubDate":"2025-07-09 14:42:53","pubDateTZ":"UTC","image_url":"https://img.haarets.co.il/bs/00000197-ef99-de26-a1ff-ffdba1bb0000/b2/b2/853fad2a497b84503f15b75b0bde/021873.jpg?cmsprod=&height=630&precrop=2400%2C1395%2Cx0%2Cy121&width=1200","video_url":null,"source_id":"haaretz","source_name":"Haaretz","source_priority":81949,"source_url":"https://www.haaretz.co.il","source_icon":"https://n.bytvi.com/haaretz.png","language":"hebrew","country":["israel"],"category":["top"],"sentiment":"ONLY AVAILABLE IN PROFESSIONAL AND CORPORATE PLANS","sentiment_stats":"ONLY AVAILABLE IN PROFESSIONAL AND CORPORATE PLANS","ai_tag":"ONLY AVAILABLE IN PROFESSIONAL AND CORPORATE PLANS","ai_region":"ONLY AVAILABLE IN CORPORATE PLANS","ai_org":"ONLY AVAILABLE IN CORPORATE PLANS","duplicate":false},{"article_id":"a7e77c354d118e003a66cd837d80cc07","title":"טרויסט סקיוריטיז מורידה את מחיר היעד של מניית ונדיז ל-14$ בעקבות רבעון שני חלש","link":"https://il.investing.com/news/analyst-ratings/article-93CH-566645","keywords":null,"creator":["Investing.com"],"description":null,"content":"ONLY AVAILABLE IN PAID PLANS","pubDate":"2025-07-09 14:42:29","pubDateTZ":"UTC","image_url":"https://i-invdn-com.investing.com/news/news_headline_rolled_108x81.jpg","video_url":null,"source_id":"investing_il","source_name":"Investing","source_priority":1143,"source_url":"https://il.investing.com","source_icon":"https://n.bytvi.com/investing_il.png","language":"hebrew","country":["israel"],"category":["top"],"sentiment":"ONLY AVAILABLE IN PROFESSIONAL AND CORPORATE PLANS","sentiment_stats":"ONLY AVAILABLE IN PROFESSIONAL AND CORPORATE PLANS","ai_tag":"ONLY AVAILABLE IN PROFESSIONAL AND CORPORATE PLANS","ai_region":"ONLY AVAILABLE IN CORPORATE PLANS","ai_org":"ONLY AVAILABLE IN CORPORATE PLANS","duplicate":false},{"article_id":"c0ece511e426a07874027813a6d5fa13","title":"חמישה נפצעו מפגיעת רכב בסמוך לטבריה, חלקם מחוסרי הכרה","link":"https://www.inn.co.il/news/673628","keywords":null,"creator":null,"description":"חמישה הולכי רגל נפגעו, חלקם באורח קשה, מפגיעת מכונית בכביש 77 סמוך לצומת פוריה. נסיבות הדריסה נבדקות.","content":"ONLY AVAILABLE IN PAID PLANS","pubDate":"2025-07-09 14:42:00","pubDateTZ":"UTC","image_url":"https://www.inn.co.il/files/pictures/0/1040449.jpg","video_url":null,"source_id":"inn","source_name":"Inn","source_priority":129730,"source_url":"https://www.inn.co.il","source_icon":"https://n.bytvi.com/inn.png","language":"hebrew","country":["israel"],"category":["top"],"sentiment":"ONLY AVAILABLE IN PROFESSIONAL AND CORPORATE PLANS","sentiment_stats":"ONLY AVAILABLE IN PROFESSIONAL AND CORPORATE PLANS","ai_tag":"ONLY AVAILABLE IN PROFESSIONAL AND CORPORATE PLANS","ai_region":"ONLY AVAILABLE IN CORPORATE PLANS","ai_org":"ONLY AVAILABLE IN CORPORATE PLANS","duplicate":false},{"article_id":"a94d8a9ec05ab6ad2d2e0bd901afbe8e","title":"ריצ'רדסון אלקטרוניקס משתפת פעולה עם פאקל טכנולוגיות בתחום מתגי הכוח","link":"https://il.investing.com/news/company-news/article-93CH-566643","keywords":null,"creator":["Investing.com"],"description":null,"content":"ONLY AVAILABLE IN PAID PLANS","pubDate":"2025-07-09 14:40:19","pubDateTZ":"UTC","image_url":"https://i-invdn-com.investing.com/news/World_News_8_M_1440052125.jpg","video_url":null,"source_id":"investing_il","source_name":"Investing","source_priority":1143,"source_url":"https://il.investing.com","source_icon":"https://n.bytvi.com/investing_il.png","language":"hebrew","country":["israel"],"category":["top"],"sentiment":"ONLY AVAILABLE IN PROFESSIONAL AND CORPORATE PLANS","sentiment_stats":"ONLY AVAILABLE IN PROFESSIONAL AND CORPORATE PLANS","ai_tag":"ONLY AVAILABLE IN PROFESSIONAL AND CORPORATE PLANS","ai_region":"ONLY AVAILABLE IN CORPORATE PLANS","ai_org":"ONLY AVAILABLE IN CORPORATE PLANS","duplicate":false},{"article_id":"508d2930e85b05e5b42adea861028531","title":"המסחר בבורסה לניירות ערך ננעל בעליות שערים","link":"https://www.maariv.co.il/breaking-news/article-1213181","keywords":null,"creator":null,"description":null,"content":"ONLY AVAILABLE IN PAID PLANS","pubDate":"2025-07-09 14:39:58","pubDateTZ":"UTC","image_url":"https://images.maariv.co.il/image/upload/f_auto,fl_lossy/c_fill,g_faces:center,h_460,w_690/990513","video_url":null,"source_id":"maariv","source_name":"מעריב","source_priority":43057,"source_url":"https://www.maariv.co.il","source_icon":"https://n.bytvi.com/maariv.png","language":"hebrew","country":["israel"],"category":["top"],"sentiment":"ONLY AVAILABLE IN PROFESSIONAL AND CORPORATE PLANS","sentiment_stats":"ONLY AVAILABLE IN PROFESSIONAL AND CORPORATE PLANS","ai_tag":"ONLY AVAILABLE IN PROFESSIONAL AND CORPORATE PLANS","ai_region":"ONLY AVAILABLE IN CORPORATE PLANS","ai_org":"ONLY AVAILABLE IN CORPORATE PLANS","duplicate":false},{"article_id":"ce9390474b73ad5df4107e09c01547fa","title":"חמישה פצועים ביניהם שלושה מחוסרי הכרה בכביש 77 סמוך לצומת פוריה בעקבות פגיעת רכב","link":"https://www.maariv.co.il/breaking-news/article-1213180","keywords":null,"creator":null,"description":null,"content":"ONLY AVAILABLE IN PAID PLANS","pubDate":"2025-07-09 14:39:46","pubDateTZ":"UTC","image_url":"https://images.maariv.co.il/image/upload/f_auto,fl_lossy/c_fill,g_faces:center,h_460,w_690/894192","video_url":null,"source_id":"maariv","source_name":"מעריב","source_priority":43057,"source_url":"https://www.maariv.co.il","source_icon":"https://n.bytvi.com/maariv.png","language":"hebrew","country":["israel"],"category":["top"],"sentiment":"ONLY AVAILABLE IN PROFESSIONAL AND CORPORATE PLANS","sentiment_stats":"ONLY AVAILABLE IN PROFESSIONAL AND CORPORATE PLANS","ai_tag":"ONLY AVAILABLE IN PROFESSIONAL AND CORPORATE PLANS","ai_region":"ONLY AVAILABLE IN CORPORATE PLANS","ai_org":"ONLY AVAILABLE IN CORPORATE PLANS","duplicate":false},{"article_id":"dc14f6de569b2b5ec343a02de4d56957","title":"ישראל פריי במוקד: זו ההחלטה של משטרת ישראל לגביו","link":"https://www.ice.co.il/local-news/news/article/1073736","keywords":null,"creator":null,"description":"העיתונאי החרדי עורר זעם בעקביו דבריו: \"העולם טוב יותר הבוקר, ללא 5 צעירים שהשתתפו באחד הפשעים האכזריים נגד האנושות\", משטרת ישראל כבר הודיעה שייחקר וקיבלה החלטה בנושא","content":"ONLY AVAILABLE IN PAID PLANS","pubDate":"2025-07-09 14:39:31","pubDateTZ":"UTC","image_url":"https://img.ice.co.il/giflib/news/rsPhoto/sz_518/rsz_615_346_F240408AVS01.jpg","video_url":null,"source_id":"ice","source_name":"Ice","source_priority":9277,"source_url":"https://www.ice.co.il","source_icon":"https://n.bytvi.com/ice.png","language":"hebrew","country":["israel"],"category":["top"],"sentiment":"ONLY AVAILABLE IN PROFESSIONAL AND CORPORATE PLANS","sentiment_stats":"ONLY AVAILABLE IN PROFESSIONAL AND CORPORATE PLANS","ai_tag":"ONLY AVAILABLE IN PROFESSIONAL AND CORPORATE PLANS","ai_region":"ONLY AVAILABLE IN CORPORATE PLANS","ai_org":"ONLY AVAILABLE IN CORPORATE PLANS","duplicate":false},{"article_id":"d00ffe7c52e341f5e97f6881e4b7f131","title":"סמסונג חושפת את Galaxy Z Flip7: מה חדש בגלקסי המתקפל?","link":"https://www.ice.co.il/digital-140/news/article/1073671","keywords":null,"creator":null,"description":"סמסונג חשפה את Galaxy Z Flip7 – המתקפל הקומפקטי שלה, עם מסך חיצוני גדול ובהיר יותר, תמיכה בבינה מלאכותית ויכולות חדשות. האם זה השדרוג שיהפוך אותו לדגם שהוא הרבה יותר מגימיק?","content":"ONLY AVAILABLE IN PAID PLANS","pubDate":"2025-07-09 14:39:31","pubDateTZ":"UTC","image_url":"https://img.ice.co.il/giflib/news/rsPhoto/sz_547/rsz_615_346_Galaxy%20Z%20Flip%207.jpg","video_url":null,"source_id":"ice","source_name":"Ice","source_priority":9277,"source_url":"https://www.ice.co.il","source_icon":"https://n.bytvi.com/ice.png","language":"hebrew","country":["israel"],"category":["top"],"sentiment":"ONLY AVAILABLE IN PROFESSIONAL AND CORPORATE PLANS","sentiment_stats":"ONLY AVAILABLE IN PROFESSIONAL AND CORPORATE PLANS","ai_tag":"ONLY AVAILABLE IN PROFESSIONAL AND CORPORATE PLANS","ai_region":"ONLY AVAILABLE IN CORPORATE PLANS","ai_org":"ONLY AVAILABLE IN CORPORATE PLANS","duplicate":false},{"article_id":"092c1f1cedd96e0bcff90b920ba69a70","title":"שדרוג השכר ב-10.5%, תוספות והטבות: אלו העובדים שירוויחו בענק","link":"https://www.ice.co.il/career/news/article/1073683","keywords":null,"creator":null,"description":"הסכם קיבוצי חדש לעובדי פרטנר. כ-2,500 עובדי החברה ייהנו מתוספות שכר מצטברות של יותר מ-10%, משדרוג תנאי הרווחה, מסבסוד לגני ילדים וקייטנות ומהגדלת התקציב לארוחות ל-51 שקל ליום. וגם: בחודש המודעות לסרטן השד תעמיד החברה רופא מומחה לבדיקות גילוי מוקדם","content":"ONLY AVAILABLE IN PAID PLANS","pubDate":"2025-07-09 14:39:31","pubDateTZ":"UTC","image_url":"https://img.ice.co.il/giflib/news/rsPhoto/sz_527/rsz_615_346_03ice20042025.jpg","video_url":null,"source_id":"ice","source_name":"Ice","source_priority":9277,"source_url":"https://www.ice.co.il","source_icon":"https://n.bytvi.com/ice.png","language":"hebrew","country":["israel"],"category":["top"],"sentiment":"ONLY AVAILABLE IN PROFESSIONAL AND CORPORATE PLANS","sentiment_stats":"ONLY AVAILABLE IN PROFESSIONAL AND CORPORATE PLANS","ai_tag":"ONLY AVAILABLE IN PROFESSIONAL AND CORPORATE PLANS","ai_region":"ONLY AVAILABLE IN CORPORATE PLANS","ai_org":"ONLY AVAILABLE IN CORPORATE PLANS","duplicate":false},{"article_id":"0037f699dad8e53bc616ee111a260800","title":"דניאל גרינברג חושפת את ההיריון המפתיע מאייל גולן: ''בהלם, בכיתי''","link":"https://www.ice.co.il/social/news/article/1073712","keywords":null,"creator":null,"description":"גרושתו של הזמר סיפרה על הדרמה הגדולה שקרתה לה בלידתו של בנה רון: \"קארין אמרה לי 'בואי נעשה בדיקה, מה יכול להיות?' עשינו בדיקה ויצא חיובי ואני הייתי בהלם רציני, בכי רציני... לא דמיינתי שאני עשיו שוב בהריון... מה הקשר? אמיתי? הרגשתי שחור''","content":"ONLY AVAILABLE IN PAID PLANS","pubDate":"2025-07-09 14:39:31","pubDateTZ":"UTC","image_url":"https://img.ice.co.il/giflib/news/rsPhoto/sz_462/rsz_615_346_29ice29052024.jpg","video_url":null,"source_id":"ice","source_name":"Ice","source_priority":9277,"source_url":"https://www.ice.co.il","source_icon":"https://n.bytvi.com/ice.png","language":"hebrew","country":["israel"],"category":["top"],"sentiment":"ONLY AVAILABLE IN PROFESSIONAL AND CORPORATE PLANS","sentiment_stats":"ONLY AVAILABLE IN PROFESSIONAL AND CORPORATE PLANS","ai_tag":"ONLY AVAILABLE IN PROFESSIONAL AND CORPORATE PLANS","ai_region":"ONLY AVAILABLE IN CORPORATE PLANS","ai_org":"ONLY AVAILABLE IN CORPORATE PLANS","duplicate":false}],"nextPage":"1752071971905443958"}
