{"status":"success","totalResults":2103,"results":[{"article_id":"d26fa1eb7970ca11c8ce4f6acb067aca","title":"המג\"ד זעק: תשובתנו נחושה - נצח ירושלים","link":"https://www.inn.co.il/news/675395","keywords":null,"creator":null,"description":"סא\"ל אביה הגר, מג\"ד גדס\"ר 6646 בטקס סיום הלחימה בסג'עיה: \"נמשיך להגיע למשימה כשנקרא\".","content":"ONLY AVAILABLE IN PAID PLANS","pubDate":"2025-07-31 11:06:41","pubDateTZ":"UTC","image_url":"https://www.inn.co.il/files/pictures/0/1195603.jpg","video_url":null,"source_id":"inn","source_name":"Inn","source_priority":129730,"source_url":"https://www.inn.co.il","source_icon":"https://n.bytvi.com/inn.png","language":"hebrew","country":["israel"],"category":["top"],"sentiment":"ONLY AVAILABLE IN PROFESSIONAL AND CORPORATE PLANS","sentiment_stats":"ONLY AVAILABLE IN PROFESSIONAL AND CORPORATE PLANS","ai_tag":"ONLY AVAILABLE IN PROFESSIONAL AND CORPORATE PLANS","ai_region":"ONLY AVAILABLE IN CORPORATE PLANS","ai_org":"ONLY AVAILABLE IN CORPORATE PLANS","ai_summary":"ONLY AVAILABLE IN PAID PLANS","ai_content":"ONLY AVAILABLE IN PROFESSIONAL AND CORPORATE PLANS","duplicate":false},{"article_id":"9859244fa24ad29cb5848188b442d17b","title":"IonQ משתפת פעולה עם אוק רידג' לבדיקת אופטימיזציה של רשת חשמל קוונטית","link":"https://il.investing.com/news/assorted/article-432SI-586471","keywords":null,"creator":["Investing.com"],"description":null,"content":"ONLY AVAILABLE IN PAID PLANS","pubDate":"2025-07-31 11:06:09","pubDateTZ":"UTC","image_url":null,"video_url":null,"source_id":"investing_il","source_name":"Investing","source_priority":1143,"source_url":"https://il.investing.com","source_icon":"https://n.bytvi.com/investing_il.png","language":"hebrew","country":["israel"],"category":["top"],"sentiment":"ONLY AVAILABLE IN PROFESSIONAL AND CORPORATE PLANS","sentiment_stats":"ONLY AVAILABLE IN PROFESSIONAL AND CORPORATE PLANS","ai_tag":"ONLY AVAILABLE IN PROFESSIONAL AND CORPORATE PLANS","ai_region":"ONLY AVAILABLE IN CORPORATE PLANS","ai_org":"ONLY AVAILABLE IN CORPORATE PLANS","ai_summary":"ONLY AVAILABLE IN PAID PLANS","ai_content":"ONLY AVAILABLE IN PROFESSIONAL AND CORPORATE PLANS","duplicate":false},{"article_id":"b05b47d52663df985579bfe93a596598","title":"שוק הקריפטו: איך יודעים מתי לקנות ולמכור?","link":"https://www.inn.co.il/news/675397","keywords":null,"creator":null,"description":"התשואות הקיצוניות, התנודתיות היומית והתחושה של השתתפות במשהו מסעיר מושכים משקיעים חדשים לשוק הקריפטו בכל גיל","content":"ONLY AVAILABLE IN PAID PLANS","pubDate":"2025-07-31 11:06:01","pubDateTZ":"UTC","image_url":"https://2.a7.org/files/pictures/781x439/1195607.jpg","video_url":null,"source_id":"inn","source_name":"Inn","source_priority":129730,"source_url":"https://www.inn.co.il","source_icon":"https://n.bytvi.com/inn.png","language":"hebrew","country":["israel"],"category":["top"],"sentiment":"ONLY AVAILABLE IN PROFESSIONAL AND CORPORATE PLANS","sentiment_stats":"ONLY AVAILABLE IN PROFESSIONAL AND CORPORATE PLANS","ai_tag":"ONLY AVAILABLE IN PROFESSIONAL AND CORPORATE PLANS","ai_region":"ONLY AVAILABLE IN CORPORATE PLANS","ai_org":"ONLY AVAILABLE IN CORPORATE PLANS","ai_summary":"ONLY AVAILABLE IN PAID PLANS","ai_content":"ONLY AVAILABLE IN PROFESSIONAL AND CORPORATE PLANS","duplicate":false},{"article_id":"7f01abcf12ceca2f434c346cc68d0fc1","title":"מחפשים בית נגיש לגיבור מעזה","link":"https://www.inn.co.il/news/675394","keywords":null,"creator":null,"description":"משפחת הקצין אלקנה לוי, שנפצע באורח קשה בעזה, פונה לציבור בבקשה לעזרה במציאת דירה נגישה עם חמישה חדרים לפחות.","content":"ONLY AVAILABLE IN PAID PLANS","pubDate":"2025-07-31 11:06:00","pubDateTZ":"UTC","image_url":"https://2.a7.org/files/pictures/781x439/1195026.jpg","video_url":null,"source_id":"inn","source_name":"Inn","source_priority":129730,"source_url":"https://www.inn.co.il","source_icon":"https://n.bytvi.com/inn.png","language":"hebrew","country":["israel"],"category":["top"],"sentiment":"ONLY AVAILABLE IN PROFESSIONAL AND CORPORATE PLANS","sentiment_stats":"ONLY AVAILABLE IN PROFESSIONAL AND CORPORATE PLANS","ai_tag":"ONLY AVAILABLE IN PROFESSIONAL AND CORPORATE PLANS","ai_region":"ONLY AVAILABLE IN CORPORATE PLANS","ai_org":"ONLY AVAILABLE IN CORPORATE PLANS","ai_summary":"ONLY AVAILABLE IN PAID PLANS","ai_content":"ONLY AVAILABLE IN PROFESSIONAL AND CORPORATE PLANS","duplicate":false},{"article_id":"ea047d88f362e45c4bb5135bd48fd520","title":"כל מה שניתן לספר על חקירת יוסף חדאד: נראה שלא מדובר בפליטת כדור","link":"https://www.maariv.co.il/news/law/article-1219824","keywords":["פליטת כדור","משטרת ישראל","יוסף חדאד","מעצר בית","חקירה"],"creator":["אלון חכמון"],"description":"במסגרת פרשת האירוע בו פלט יוסף חדאד כדור במהלך ויכוח בכביש, כפי שנטען תחילה, חדאד הגיע היום לחקירה נוספת. למעריב נודע כי המצלמות מהאזור בידי המשטרה - וזה שמה שניתן לספר עד כה","content":"ONLY AVAILABLE IN PAID PLANS","pubDate":"2025-07-31 11:05:42","pubDateTZ":"UTC","image_url":"https://images.maariv.co.il/image/upload/f_auto,fl_lossy/c_fill,g_faces:center,h_270,w_500/986813","video_url":null,"source_id":"maariv","source_name":"מעריב","source_priority":43057,"source_url":"https://www.maariv.co.il","source_icon":"https://n.bytvi.com/maariv.png","language":"hebrew","country":["israel"],"category":["top"],"sentiment":"ONLY AVAILABLE IN PROFESSIONAL AND CORPORATE PLANS","sentiment_stats":"ONLY AVAILABLE IN PROFESSIONAL AND CORPORATE PLANS","ai_tag":"ONLY AVAILABLE IN PROFESSIONAL AND CORPORATE PLANS","ai_region":"ONLY AVAILABLE IN CORPORATE PLANS","ai_org":"ONLY AVAILABLE IN CORPORATE PLANS","ai_summary":"ONLY AVAILABLE IN PAID PLANS","ai_content":"ONLY AVAILABLE IN PROFESSIONAL AND CORPORATE PLANS","duplicate":false},{"article_id":"94f6d04d92ffeffd5da3c5a8b814b443","title":"קרן פלס נפרדת בצער: ''תודה על מפגש משנה חיים''","link":"https://www.ice.co.il/tv/news/article/1077191","keywords":["שחקן","זמרת","אלון אבוטבול","פטירה","קרן פלס","מוות"],"creator":["מערכת ice"],"description":"פלס כתבה בסטורי ששיתפה על התחושות שלה בעקבות מותו בטרם עת של אלון אבוטבול: \"חבר שלי טוב ואהוב וקרוב, אתה איתי פה בהכל ותמיד תהיה. נפגשנו בעולמות הרוח, מוזיקה ותיאטרון, התקרבנו עוד ועוד כשהפכנו שכנים זרים באי קסמים יווני''","content":"ONLY AVAILABLE IN PAID PLANS","pubDate":"2025-07-31 11:05:02","pubDateTZ":"UTC","image_url":"https://img.ice.co.il/giflib/news/rsPhoto/sz_493/rsz_615_346_17ice27112024.jpg","video_url":null,"source_id":"ice","source_name":"Ice","source_priority":9277,"source_url":"https://www.ice.co.il","source_icon":"https://n.bytvi.com/ice.png","language":"hebrew","country":["israel"],"category":["top"],"sentiment":"ONLY AVAILABLE IN PROFESSIONAL AND CORPORATE PLANS","sentiment_stats":"ONLY AVAILABLE IN PROFESSIONAL AND CORPORATE PLANS","ai_tag":"ONLY AVAILABLE IN PROFESSIONAL AND CORPORATE PLANS","ai_region":"ONLY AVAILABLE IN CORPORATE PLANS","ai_org":"ONLY AVAILABLE IN CORPORATE PLANS","ai_summary":"ONLY AVAILABLE IN PAID PLANS","ai_content":"ONLY AVAILABLE IN PROFESSIONAL AND CORPORATE PLANS","duplicate":false},{"article_id":"4821492a24a653e9f7a4b34eac96a3c1","title":"בשורה משמחת לצרכנים: שיתוף הפעולה החדש בין רמי לוי לפנינה רוזנבלום","link":"https://www.ice.co.il/consumerism/news/article/1077238","keywords":["איפור","גוד פארם","טיפוח","אוהד סנדלר","רמי לוי","אדם פרידלדר","פנינה רוזנבלום"],"creator":["ענת סימן טוב"],"description":"איש העסקים רמי לוי חובר לפנינה רוזנבלום ברשת גוד פארם, עם מוצרים חדשים וייחודים של אשת העסקים במחירים נגישים. כל הפרטים","content":"ONLY AVAILABLE IN PAID PLANS","pubDate":"2025-07-31 11:05:02","pubDateTZ":"UTC","image_url":"https://img.ice.co.il/giflib/news/rsPhoto/sz_548/rsz_615_346_13ice10072025.jpg","video_url":null,"source_id":"ice","source_name":"Ice","source_priority":9277,"source_url":"https://www.ice.co.il","source_icon":"https://n.bytvi.com/ice.png","language":"hebrew","country":["israel"],"category":["top"],"sentiment":"ONLY AVAILABLE IN PROFESSIONAL AND CORPORATE PLANS","sentiment_stats":"ONLY AVAILABLE IN PROFESSIONAL AND CORPORATE PLANS","ai_tag":"ONLY AVAILABLE IN PROFESSIONAL AND CORPORATE PLANS","ai_region":"ONLY AVAILABLE IN CORPORATE PLANS","ai_org":"ONLY AVAILABLE IN CORPORATE PLANS","ai_summary":"ONLY AVAILABLE IN PAID PLANS","ai_content":"ONLY AVAILABLE IN PROFESSIONAL AND CORPORATE PLANS","duplicate":false},{"article_id":"b824698ec1423a941504011209dd1273","title":"כוכבי האח הגדול על אייל גולן: \"הוא לא אפיפיור מה רוצים ממנו?\"","link":"https://www.ice.co.il/media/news/article/1077233","keywords":["מוסר","רמת גן","האח הגדול","אייל גולן","כרמל שאמה הכהן","בית משפט","פרשת משחקי חברה"],"creator":["מערכת ice"],"description":"דיירי העבר מעלים מחדש את פרשת אייל גולן לדיון. לפי התסריטאי אינדל קבדה, \"אייל גולן לא אפיפיור\", והמוסר צריך להימדד בבית המשפט","content":"ONLY AVAILABLE IN PAID PLANS","pubDate":"2025-07-31 11:05:02","pubDateTZ":"UTC","image_url":"https://img.ice.co.il/giflib/news/rsPhoto/sz_546/rsz_615_346_6ice03072025.jpg","video_url":null,"source_id":"ice","source_name":"Ice","source_priority":9277,"source_url":"https://www.ice.co.il","source_icon":"https://n.bytvi.com/ice.png","language":"hebrew","country":["israel"],"category":["top"],"sentiment":"ONLY AVAILABLE IN PROFESSIONAL AND CORPORATE PLANS","sentiment_stats":"ONLY AVAILABLE IN PROFESSIONAL AND CORPORATE PLANS","ai_tag":"ONLY AVAILABLE IN PROFESSIONAL AND CORPORATE PLANS","ai_region":"ONLY AVAILABLE IN CORPORATE PLANS","ai_org":"ONLY AVAILABLE IN CORPORATE PLANS","ai_summary":"ONLY AVAILABLE IN PAID PLANS","ai_content":"ONLY AVAILABLE IN PROFESSIONAL AND CORPORATE PLANS","duplicate":false},{"article_id":"0af99f2f04e396fa02c2fb2c0d00182c","title":"בשורה אדירה לנהגים: זו העיר שתחסוך הרבה זמן עם מחלף חדש","link":"https://www.ice.co.il/auto/news/article/1077232","keywords":["יקב רמת הגולן","צפון","משרד התחבורה","נתיבי ישראל","מחלף","קצרין","כביש"],"creator":["מערכת ice"],"description":"שדרוג כביש 91 והקמת מחלף מחניים מתחיל: בהובלת השרה רגב: משרד האוצר העביר למשרד התחבורה תקציב של 20 מיליון שקלים לחיבור הגולן לגליל","content":"ONLY AVAILABLE IN PAID PLANS","pubDate":"2025-07-31 11:05:02","pubDateTZ":"UTC","image_url":"https://img.ice.co.il/giflib/news/rsPhoto/sz_383/rsz_615_346_%D7%AA%D7%9E%D7%95%D7%A0%D7%AA%20%D7%A8%D7%97%D7%A4%D7%9F%20-%20%D7%A7%D7%A6%D7%A8%D7%99%D7%9F%20.%20%D7%A8%D7%95%D7%91%D7%A2%2012.%20%D7%A6%D7%99%D7%9C%D7%95%D7%9D%20-%20%D7%9E%D7%95%D7%98%D7%99%20%D7%A9%D7%95%D7%A8%D7%A5.jpg","video_url":null,"source_id":"ice","source_name":"Ice","source_priority":9277,"source_url":"https://www.ice.co.il","source_icon":"https://n.bytvi.com/ice.png","language":"hebrew","country":["israel"],"category":["top"],"sentiment":"ONLY AVAILABLE IN PROFESSIONAL AND CORPORATE PLANS","sentiment_stats":"ONLY AVAILABLE IN PROFESSIONAL AND CORPORATE PLANS","ai_tag":"ONLY AVAILABLE IN PROFESSIONAL AND CORPORATE PLANS","ai_region":"ONLY AVAILABLE IN CORPORATE PLANS","ai_org":"ONLY AVAILABLE IN CORPORATE PLANS","ai_summary":"ONLY AVAILABLE IN PAID PLANS","ai_content":"ONLY AVAILABLE IN PROFESSIONAL AND CORPORATE PLANS","duplicate":false},{"article_id":"a96db0294995341b1fdf4536303ab6b9","title":"ב-2.3 מיליון שקל: הולמס פלייס מגיעה לעיר הזו לראשונה","link":"https://www.ice.co.il/sport_news/news/article/1077241","keywords":["רכישה","מכון כושר","נתיבות","הולמס פלייס","מועדון כושר","עסקה","כושר"],"creator":["מערכת ice"],"description":"הולמס פלייס רוכשת את מועדון הכושר \"פיטלנד\" בנתיבות בעסקה של מיליוני שקלים. העסקה צפויה להסתיים ב-1 בספטמבר 2025, כאשר הרכישה כוללת את כלל הזכויות במועדון, הציוד, לקוחות המועדון ואת המוניטין שלו","content":"ONLY AVAILABLE IN PAID PLANS","pubDate":"2025-07-31 11:05:01","pubDateTZ":"UTC","image_url":"https://img.ice.co.il/giflib/news/rsPhoto/sz_462/rsz_615_346_11ice29052024.jpg","video_url":null,"source_id":"ice","source_name":"Ice","source_priority":9277,"source_url":"https://www.ice.co.il","source_icon":"https://n.bytvi.com/ice.png","language":"hebrew","country":["israel"],"category":["top"],"sentiment":"ONLY AVAILABLE IN PROFESSIONAL AND CORPORATE PLANS","sentiment_stats":"ONLY AVAILABLE IN PROFESSIONAL AND CORPORATE PLANS","ai_tag":"ONLY AVAILABLE IN PROFESSIONAL AND CORPORATE PLANS","ai_region":"ONLY AVAILABLE IN CORPORATE PLANS","ai_org":"ONLY AVAILABLE IN CORPORATE PLANS","ai_summary":"ONLY AVAILABLE IN PAID PLANS","ai_content":"ONLY AVAILABLE IN PROFESSIONAL AND CORPORATE PLANS","duplicate":false}],"nextPage":"1753959901994039267"}
