{"status":"success","totalResults":2271,"results":[{"article_id":"67ea9921b88bfe3a9e853569d5f283d9","link":"https://www.haaretz.co.il/news/politics/2026-01-06/ty-article/.premium/0000019b-92e6-dd39-a7ff-fbfefea40000","title":"צה\"ל פשט על קמפוס ביר זית בזמן הפגנת סטודנטים ועיכב את סגן הנשיא האוניברסיטה","description":"לפי הנהלת המוסד, הצבא פשט על הקמפוס שליד רמאללה בזמן עצרת תמיכה באסירים פלסטינים ועשה שימוש בירי חי וגז מדמיע. הסהר האדום הודיע על 11 פצועים. צה\"ל: \"התפתחה הפרת סדר שכללה ידויי אבנים לעבר הכוחות באופן שהיווה עליהם איום\"","content":"ONLY AVAILABLE IN PAID PLANS","keywords":null,"creator":["רואן סלימאן"],"language":"hebrew","country":["israel"],"category":["top"],"datatype":"news","pubDate":"2026-01-06 16:29:08","pubDateTZ":"UTC","fetched_at":"2026-01-06 16:47:05","image_url":"https://img.haarets.co.il/bs/0000019b-92e6-dd39-a7ff-fbfefea40000/33/2f/6b4d25e346dabc995a9794a45ab5/303044.jpg?cmsprod=&height=630&precrop=2400%2C1395%2Cx0%2Cy0&width=1200","video_url":null,"source_id":"haaretz","source_name":"Haaretz","source_priority":81949,"source_url":"https://www.haaretz.co.il","source_icon":"https://n.bytvi.com/haaretz.png","sentiment":"ONLY AVAILABLE IN PROFESSIONAL AND CORPORATE PLANS","sentiment_stats":"ONLY AVAILABLE IN PROFESSIONAL AND CORPORATE PLANS","ai_tag":"ONLY AVAILABLE IN PROFESSIONAL AND CORPORATE PLANS","ai_region":"ONLY AVAILABLE IN CORPORATE PLANS","ai_org":"ONLY AVAILABLE IN CORPORATE PLANS","ai_summary":"ONLY AVAILABLE IN PAID PLANS","duplicate":false},{"article_id":"d0cf50ff183f67c07312a9f5964972ba","link":"https://www.maariv.co.il/breaking-news/article-1270025","title":"כוחות צה\"ל פיזרו התקהלות אלימה במרחב אוניברסיטת ביר זית בחטיבת בנימין","description":null,"content":"ONLY AVAILABLE IN PAID PLANS","keywords":["דה-פוסט","פוסט","מעריב","ngrhc","סופהשבוע","maariv"],"creator":["גלעד מורג"],"language":"hebrew","country":["israel"],"category":["top","lifestyle"],"datatype":"news","pubDate":"2026-01-06 16:28:14","pubDateTZ":"UTC","fetched_at":"2026-01-06 16:44:30","image_url":"https://images.maariv.co.il/image/upload/f_auto,fl_lossy/c_fill,g_faces:center,h_438,w_778/1048860","video_url":null,"source_id":"maariv","source_name":"מעריב","source_priority":43057,"source_url":"https://www.maariv.co.il","source_icon":"https://n.bytvi.com/maariv.png","sentiment":"ONLY AVAILABLE IN PROFESSIONAL AND CORPORATE PLANS","sentiment_stats":"ONLY AVAILABLE IN PROFESSIONAL AND CORPORATE PLANS","ai_tag":"ONLY AVAILABLE IN PROFESSIONAL AND CORPORATE PLANS","ai_region":"ONLY AVAILABLE IN CORPORATE PLANS","ai_org":"ONLY AVAILABLE IN CORPORATE PLANS","ai_summary":"ONLY AVAILABLE IN PAID PLANS","duplicate":false},{"article_id":"f60205765cb0872fb43bb0c155fad03d","link":"https://il.investing.com/news/company-news/article-93CH-721146","title":"Nvidia מובילה את האחזקות העיקריות של Polar Capital Technology Trust עם 10%","description":null,"content":"ONLY AVAILABLE IN PAID PLANS","keywords":null,"creator":["investing.com"],"language":"hebrew","country":["israel"],"category":["business","top","lifestyle"],"datatype":"news","pubDate":"2026-01-06 16:27:18","pubDateTZ":"UTC","fetched_at":"2026-01-06 16:34:49","image_url":"https://i-invdn-com.investing.com/news/world_news_2_108x81.jpg","video_url":null,"source_id":"investing_il","source_name":"Investing","source_priority":1143,"source_url":"https://il.investing.com","source_icon":"https://n.bytvi.com/investing_il.png","sentiment":"ONLY AVAILABLE IN PROFESSIONAL AND CORPORATE PLANS","sentiment_stats":"ONLY AVAILABLE IN PROFESSIONAL AND CORPORATE PLANS","ai_tag":"ONLY AVAILABLE IN PROFESSIONAL AND CORPORATE PLANS","ai_region":"ONLY AVAILABLE IN CORPORATE PLANS","ai_org":"ONLY AVAILABLE IN CORPORATE PLANS","ai_summary":"ONLY AVAILABLE IN PAID PLANS","duplicate":false},{"article_id":"6e2277211ff348bcfa5ed3f70504b314","link":"https://il.investing.com/news/company-news/article-93CH-721145","title":"מניית אלדורדו גולד מגיעה לשיא של 52 שבועות בשער של 37.61 דולר","description":null,"content":"ONLY AVAILABLE IN PAID PLANS","keywords":null,"creator":["investing.com"],"language":"hebrew","country":["israel"],"category":["top"],"datatype":"news","pubDate":"2026-01-06 16:26:50","pubDateTZ":"UTC","fetched_at":"2026-01-06 16:34:49","image_url":"https://i-invdn-com.investing.com/news/world_news_2_108x81.jpg","video_url":null,"source_id":"investing_il","source_name":"Investing","source_priority":1143,"source_url":"https://il.investing.com","source_icon":"https://n.bytvi.com/investing_il.png","sentiment":"ONLY AVAILABLE IN PROFESSIONAL AND CORPORATE PLANS","sentiment_stats":"ONLY AVAILABLE IN PROFESSIONAL AND CORPORATE PLANS","ai_tag":"ONLY AVAILABLE IN PROFESSIONAL AND CORPORATE PLANS","ai_region":"ONLY AVAILABLE IN CORPORATE PLANS","ai_org":"ONLY AVAILABLE IN CORPORATE PLANS","ai_summary":"ONLY AVAILABLE IN PAID PLANS","duplicate":false},{"article_id":"05fc170bdc2ffd8d13829eafb2044aae","link":"https://il.investing.com/news/company-news/article-93CH-721144","title":"מניית פורטונה מיינינג קורפ מגיעה לשיא כל הזמנים ב-10.39 דולר","description":null,"content":"ONLY AVAILABLE IN PAID PLANS","keywords":null,"creator":["investing.com"],"language":"hebrew","country":["israel"],"category":["business","top"],"datatype":"news","pubDate":"2026-01-06 16:26:00","pubDateTZ":"UTC","fetched_at":"2026-01-06 16:34:49","image_url":"https://i-invdn-com.investing.com/news/world_news_2_108x81.jpg","video_url":null,"source_id":"investing_il","source_name":"Investing","source_priority":1143,"source_url":"https://il.investing.com","source_icon":"https://n.bytvi.com/investing_il.png","sentiment":"ONLY AVAILABLE IN PROFESSIONAL AND CORPORATE PLANS","sentiment_stats":"ONLY AVAILABLE IN PROFESSIONAL AND CORPORATE PLANS","ai_tag":"ONLY AVAILABLE IN PROFESSIONAL AND CORPORATE PLANS","ai_region":"ONLY AVAILABLE IN CORPORATE PLANS","ai_org":"ONLY AVAILABLE IN CORPORATE PLANS","ai_summary":"ONLY AVAILABLE IN PAID PLANS","duplicate":false},{"article_id":"8bf22da8a2e7644be4089932349a467d","link":"https://www.maariv.co.il/news/law/article-1270019","title":"אהרן ברק רותח: הכנסת ביטלה את הלכת אפרופים - \"התכלית היא שונה\"","description":"לאור החלטת הכנסת לבטל את \"הלכת אפרופים\" של אהרן ברק, עו''ד אייל רוזובסקי, שותף במשרד \"מיתר\", שוחח על המהלך ההיסטורי עם ענת דוידוב בתוכניתה ברדיו 103FM: \"ציון דרך - אבל לא דרמה\"","content":"ONLY AVAILABLE IN PAID PLANS","keywords":["חוזה","רדיו 103 fm","103fm","דיני חוזים","אהרן ברק"],"creator":null,"language":"hebrew","country":["israel"],"category":["top"],"datatype":"news","pubDate":"2026-01-06 16:24:33","pubDateTZ":"UTC","fetched_at":"2026-01-06 16:44:30","image_url":"https://images.maariv.co.il/image/upload/f_auto,fl_lossy/c_fill,g_faces:center,w_1200/869775","video_url":null,"source_id":"maariv","source_name":"מעריב","source_priority":43057,"source_url":"https://www.maariv.co.il","source_icon":"https://n.bytvi.com/maariv.png","sentiment":"ONLY AVAILABLE IN PROFESSIONAL AND CORPORATE PLANS","sentiment_stats":"ONLY AVAILABLE IN PROFESSIONAL AND CORPORATE PLANS","ai_tag":"ONLY AVAILABLE IN PROFESSIONAL AND CORPORATE PLANS","ai_region":"ONLY AVAILABLE IN CORPORATE PLANS","ai_org":"ONLY AVAILABLE IN CORPORATE PLANS","ai_summary":"ONLY AVAILABLE IN PAID PLANS","duplicate":false},{"article_id":"5ba23260d32206c40a3c5660523b3381","link":"https://www.inn.co.il/news/687072","title":"\"חיבור לרשעים\": הקרב הפנים-חרדי על חוק הגיוס","description":"ב\"יתד נאמן\" הסבירו מדוע חשוב לתמוך בחוק הגיוס. \"על כולם מוציאים צווי גיוס, צווי מעצר וסנקציות כלכליות. חוק הגיוס כבר קרה\".","content":"ONLY AVAILABLE IN PAID PLANS","keywords":null,"creator":null,"language":"hebrew","country":["israel"],"category":["top","lifestyle"],"datatype":"news","pubDate":"2026-01-06 16:22:00","pubDateTZ":"UTC","fetched_at":"2026-01-06 17:48:00","image_url":"https://2.a7.org/files/pictures/781x439/1160903.jpg","video_url":null,"source_id":"inn","source_name":"Inn","source_priority":129730,"source_url":"https://www.inn.co.il","source_icon":"https://n.bytvi.com/inn.png","sentiment":"ONLY AVAILABLE IN PROFESSIONAL AND CORPORATE PLANS","sentiment_stats":"ONLY AVAILABLE IN PROFESSIONAL AND CORPORATE PLANS","ai_tag":"ONLY AVAILABLE IN PROFESSIONAL AND CORPORATE PLANS","ai_region":"ONLY AVAILABLE IN CORPORATE PLANS","ai_org":"ONLY AVAILABLE IN CORPORATE PLANS","ai_summary":"ONLY AVAILABLE IN PAID PLANS","duplicate":false},{"article_id":"a22329aaf2fdc534dd4fbde403448d89","link":"https://il.investing.com/news/analyst-ratings/article-93CH-721143","title":"ריימונד ג’יימס מאשררת המלצת \"קנייה חזקה\" למנית סטוק טיישה ג’ין תרפיס","description":null,"content":"ONLY AVAILABLE IN PAID PLANS","keywords":null,"creator":["investing.com"],"language":"hebrew","country":["israel"],"category":["top","lifestyle"],"datatype":"news","pubDate":"2026-01-06 16:21:13","pubDateTZ":"UTC","fetched_at":"2026-01-06 16:34:49","image_url":"https://i-invdn-com.investing.com/news/world_news_2_108x81.jpg","video_url":null,"source_id":"investing_il","source_name":"Investing","source_priority":1143,"source_url":"https://il.investing.com","source_icon":"https://n.bytvi.com/investing_il.png","sentiment":"ONLY AVAILABLE IN PROFESSIONAL AND CORPORATE PLANS","sentiment_stats":"ONLY AVAILABLE IN PROFESSIONAL AND CORPORATE PLANS","ai_tag":"ONLY AVAILABLE IN PROFESSIONAL AND CORPORATE PLANS","ai_region":"ONLY AVAILABLE IN CORPORATE PLANS","ai_org":"ONLY AVAILABLE IN CORPORATE PLANS","ai_summary":"ONLY AVAILABLE IN PAID PLANS","duplicate":false},{"article_id":"3384b48840e2ad1445d27ca6822b3e97","link":"https://il.investing.com/news/insider-trading-news/article-93CH-721142","title":"מנכ\"ל סנטרל סקיוריטיז היל רוכש מניות חברה בשווי 25,455$","description":null,"content":"ONLY AVAILABLE IN PAID PLANS","keywords":null,"creator":["investing.com"],"language":"hebrew","country":["israel"],"category":["business","top"],"datatype":"news","pubDate":"2026-01-06 16:19:25","pubDateTZ":"UTC","fetched_at":"2026-01-06 16:34:49","image_url":"https://i-invdn-com.investing.com/news/world_news_2_108x81.jpg","video_url":null,"source_id":"investing_il","source_name":"Investing","source_priority":1143,"source_url":"https://il.investing.com","source_icon":"https://n.bytvi.com/investing_il.png","sentiment":"ONLY AVAILABLE IN PROFESSIONAL AND CORPORATE PLANS","sentiment_stats":"ONLY AVAILABLE IN PROFESSIONAL AND CORPORATE PLANS","ai_tag":"ONLY AVAILABLE IN PROFESSIONAL AND CORPORATE PLANS","ai_region":"ONLY AVAILABLE IN CORPORATE PLANS","ai_org":"ONLY AVAILABLE IN CORPORATE PLANS","ai_summary":"ONLY AVAILABLE IN PAID PLANS","duplicate":false},{"article_id":"c735c6689ddba99d8982a4c95e9be8e7","link":"https://www.maariv.co.il/breaking-news/article-1270020","title":"דיווח על קולות ירי סמוך לארמון הנשיאות בעדן שבתימן","description":null,"content":"ONLY AVAILABLE IN PAID PLANS","keywords":["דה-פוסט","פוסט","מעריב","ngrhc","סופהשבוע","maariv"],"creator":["גלעד מורג"],"language":"hebrew","country":["israel"],"category":["top","lifestyle"],"datatype":"news","pubDate":"2026-01-06 16:18:12","pubDateTZ":"UTC","fetched_at":"2026-01-06 16:44:27","image_url":"https://images.maariv.co.il/image/upload/f_auto,fl_lossy/c_fill,g_faces:center,h_438,w_778/894192","video_url":null,"source_id":"maariv","source_name":"מעריב","source_priority":43057,"source_url":"https://www.maariv.co.il","source_icon":"https://n.bytvi.com/maariv.png","sentiment":"ONLY AVAILABLE IN PROFESSIONAL AND CORPORATE PLANS","sentiment_stats":"ONLY AVAILABLE IN PROFESSIONAL AND CORPORATE PLANS","ai_tag":"ONLY AVAILABLE IN PROFESSIONAL AND CORPORATE PLANS","ai_region":"ONLY AVAILABLE IN CORPORATE PLANS","ai_org":"ONLY AVAILABLE IN CORPORATE PLANS","ai_summary":"ONLY AVAILABLE IN PAID PLANS","duplicate":false}],"nextPage":"1767716292549668728"}
