{"status":"success","totalResults":1532,"results":[{"article_id":"a3c5d0fccbd0c544f1c98645720238ff","link":"https://www.israelhayom.co.il/news/local/article/20371814","title":"טרגדיה בכביש 60: נער בן 16 נהרג בתאונת דרכים קטלנית","description":"רוכב אופניים חשמליים נפגע מרכב סמוך לצומת בין ענון • צוותי מד\"א מצאו אותו ללא דופק וללא נשימה, ונאלצו לקבוע את מותו במקום • פרמדיק מד\"א דרור עיני וחובש מד\"א בני טנא סיפרו: \"הוא היה מחוסר הכרה, ללא דופק וללא נשימה, עם חבלות קשות מאוד בגופו\"","content":"ONLY AVAILABLE IN PAID PLANS","keywords":["תאונת דרכים. הרוגים","תאונת דרכים"],"creator":["לידור סולטן"],"language":"hebrew","country":["israel"],"category":["lifestyle","top"],"datatype":"news","pubDate":"2026-04-21 03:55:41","pubDateTZ":"UTC","fetched_at":"2026-04-21 04:03:58","image_url":"https://www.israelhayom.co.il/wp-content/uploads/2026/04/21/21/WhatsApp-Image-2026-04-21-at-06.42.39.jpeg","video_url":null,"source_id":"israelhayom","source_name":"ישראל היום","source_priority":13660,"source_url":"https://www.israelhayom.co.il","source_icon":"https://n.bytvi.com/israelhayom.jpg","sentiment":"ONLY AVAILABLE IN PROFESSIONAL AND CORPORATE PLANS","sentiment_stats":"ONLY AVAILABLE IN PROFESSIONAL AND CORPORATE PLANS","ai_tag":"ONLY AVAILABLE IN PROFESSIONAL AND CORPORATE PLANS","ai_region":"ONLY AVAILABLE IN CORPORATE PLANS","ai_org":"ONLY AVAILABLE IN CORPORATE PLANS","ai_summary":"ONLY AVAILABLE IN PAID PLANS","duplicate":false},{"article_id":"6441430066f632883bb9744daa58550a","link":"https://www.inn.co.il/news/695045","title":"ב-11:00 תישמע צפירה בת שתי דקות","description":"ישראל מתייחדת עם זכר הנופלים: ב-08:30, בהיכל הזיכרון הממלכתי בהר הרצל שבירושלים, תתקיים הקראת שמותיהם של חללי מערכות ישראל.","content":"ONLY AVAILABLE IN PAID PLANS","keywords":["יום הזיכרון"],"creator":["ערוץ 7"],"language":"hebrew","country":["israel"],"category":["lifestyle","top"],"datatype":"news","pubDate":"2026-04-21 03:54:03","pubDateTZ":"UTC","fetched_at":"2026-04-21 04:39:09","image_url":"https://2.a7.org/files/pictures/000/undefined.jpg","video_url":null,"source_id":"inn","source_name":"Inn","source_priority":129730,"source_url":"https://www.inn.co.il","source_icon":"https://n.bytvi.com/inn.png","sentiment":"ONLY AVAILABLE IN PROFESSIONAL AND CORPORATE PLANS","sentiment_stats":"ONLY AVAILABLE IN PROFESSIONAL AND CORPORATE PLANS","ai_tag":"ONLY AVAILABLE IN PROFESSIONAL AND CORPORATE PLANS","ai_region":"ONLY AVAILABLE IN CORPORATE PLANS","ai_org":"ONLY AVAILABLE IN CORPORATE PLANS","ai_summary":"ONLY AVAILABLE IN PAID PLANS","duplicate":false},{"article_id":"44a1714211105433c1c6ae8453c8d4e3","link":"https://il.investing.com/news/company-news/article-93CH-816816","title":"ספרוס ביוסיינסס מתמחרת הנפקה ציבורית של 60 מיליון דולר ב-50 דולר למנייה","description":"ספרוס ביוסיינסס מתמחרת הנפקה ציבורית של 60 מיליון דולר ב-50 דולר למנייה","content":"ONLY AVAILABLE IN PAID PLANS","keywords":null,"creator":["investing.com"],"language":"hebrew","country":["israel"],"category":["business","top"],"datatype":"news","pubDate":"2026-04-21 03:51:44","pubDateTZ":"UTC","fetched_at":"2026-04-21 04:02:11","image_url":"https://i-invdn-com.investing.com/news/LYNXNPEB6J0AJ_L.jpg","video_url":null,"source_id":"investing_il","source_name":"Investing","source_priority":1143,"source_url":"https://il.investing.com","source_icon":"https://n.bytvi.com/investing_il.png","sentiment":"ONLY AVAILABLE IN PROFESSIONAL AND CORPORATE PLANS","sentiment_stats":"ONLY AVAILABLE IN PROFESSIONAL AND CORPORATE PLANS","ai_tag":"ONLY AVAILABLE IN PROFESSIONAL AND CORPORATE PLANS","ai_region":"ONLY AVAILABLE IN CORPORATE PLANS","ai_org":"ONLY AVAILABLE IN CORPORATE PLANS","ai_summary":"ONLY AVAILABLE IN PAID PLANS","duplicate":false},{"article_id":"281fb60c6cd9bc3cfb5aef540045e069","link":"https://www.israelhayom.co.il/tech/tech-news/article/20371093","title":"\"ברוכים הבאים לעידן הכוח\": החזון המפחיד של מנכ\"ל פלנטיר","description":"ענקית ניתוח הנתונים המזוהה עם זרועות הביטחון האמריקניות, פרסמה בסוף השבוע \"מניפסט\" בן 22 נקודות שנקרא כמו נאום של נבל-על בסרט קומיקס • משירות חובה לכולם ועד לביטול ה\"ניטרול\" של גרמניה ויפן • המניפסט של אלכס קארפ מבהיר שעידן האפליקציות החמודות הסתיים, והעידן של \"הכוח הקשה\" התחיל","content":"ONLY AVAILABLE IN PAID PLANS","keywords":null,"creator":["שחר שפירו"],"language":"hebrew","country":["israel"],"category":["top"],"datatype":"news","pubDate":"2026-04-21 03:49:31","pubDateTZ":"UTC","fetched_at":"2026-04-21 04:03:58","image_url":"https://www.israelhayom.co.il/wp-content/uploads/2026/02/17/17/12664560.jpg","video_url":null,"source_id":"israelhayom","source_name":"ישראל היום","source_priority":13660,"source_url":"https://www.israelhayom.co.il","source_icon":"https://n.bytvi.com/israelhayom.jpg","sentiment":"ONLY AVAILABLE IN PROFESSIONAL AND CORPORATE PLANS","sentiment_stats":"ONLY AVAILABLE IN PROFESSIONAL AND CORPORATE PLANS","ai_tag":"ONLY AVAILABLE IN PROFESSIONAL AND CORPORATE PLANS","ai_region":"ONLY AVAILABLE IN CORPORATE PLANS","ai_org":"ONLY AVAILABLE IN CORPORATE PLANS","ai_summary":"ONLY AVAILABLE IN PAID PLANS","duplicate":false},{"article_id":"070785819367c39ec823664542359f6a","link":"https://www.haaretz.co.il/gallery/music/2026-04-21/ty-article-magazine/.premium/0000019d-aa0a-d834-abbd-fbcaaaa50000","title":"אמג'ד מריח: \"חלק מהיהודים שמאזינים שונאים ערבים, אבל ברגע שהמוזיקה מתנגנת הכל נעלם\"","description":"אמג'ד מריח הרחיק עד אוסטרליה כדי לפתור את משבר הזהות שחש כדרוזי. כשחזר הפך לאחד מנגני האקורדיון הערבים הבודדים","content":"ONLY AVAILABLE IN PAID PLANS","keywords":null,"creator":["בן שלו"],"language":"hebrew","country":["israel"],"category":["lifestyle","top"],"datatype":"multimedia","pubDate":"2026-04-21 03:44:01","pubDateTZ":"UTC","fetched_at":"2026-04-21 04:08:45","image_url":"https://img.haarets.co.il/bs/0000019d-ab0e-d45b-a39f-ef0eb2480000/54/68/366e69b546729e4dfcc7aefd6753/632342.jpg?height=81","video_url":null,"source_id":"haaretz","source_name":"Haaretz","source_priority":81949,"source_url":"https://www.haaretz.co.il","source_icon":"https://n.bytvi.com/haaretz.png","sentiment":"ONLY AVAILABLE IN PROFESSIONAL AND CORPORATE PLANS","sentiment_stats":"ONLY AVAILABLE IN PROFESSIONAL AND CORPORATE PLANS","ai_tag":"ONLY AVAILABLE IN PROFESSIONAL AND CORPORATE PLANS","ai_region":"ONLY AVAILABLE IN CORPORATE PLANS","ai_org":"ONLY AVAILABLE IN CORPORATE PLANS","ai_summary":"ONLY AVAILABLE IN PAID PLANS","duplicate":false},{"article_id":"d59e1af65be7cc3ac5c90fa80b6c7d8c","link":"https://www.israelhayom.co.il/lifestyle/beauty/article/20368091","title":"כובש את הרשת: למה כולם מרססים ספריי לשיער על צווארון החולצה?","description":"הטיפ המפתיע שמסתובב ברשת מבטיח להעלים כתמי איפור תוך דקות • כך ספריי לשיער הפך לפתרון מפתיע בארון הבגדים","content":"ONLY AVAILABLE IN PAID PLANS","keywords":null,"creator":["סוכנויות הידיעות"],"language":"hebrew","country":["israel"],"category":["lifestyle","top"],"datatype":"news","pubDate":"2026-04-21 03:42:55","pubDateTZ":"UTC","fetched_at":"2026-04-21 04:03:58","image_url":"https://www.israelhayom.co.il/wp-content/uploads/2026/04/20/20/GettyImages-2238081882.jpg.jpeg","video_url":null,"source_id":"israelhayom","source_name":"ישראל היום","source_priority":13660,"source_url":"https://www.israelhayom.co.il","source_icon":"https://n.bytvi.com/israelhayom.jpg","sentiment":"ONLY AVAILABLE IN PROFESSIONAL AND CORPORATE PLANS","sentiment_stats":"ONLY AVAILABLE IN PROFESSIONAL AND CORPORATE PLANS","ai_tag":"ONLY AVAILABLE IN PROFESSIONAL AND CORPORATE PLANS","ai_region":"ONLY AVAILABLE IN CORPORATE PLANS","ai_org":"ONLY AVAILABLE IN CORPORATE PLANS","ai_summary":"ONLY AVAILABLE IN PAID PLANS","duplicate":false},{"article_id":"98a42f5ce1211c47489711001e0319d3","link":"https://www.israelhayom.co.il/culture/stage/article/20366502","title":"מהלך ייחודי ליום הזיכרון: מנציחים נופלים - בכתב ידם","description":"מיזם \"אות זיכרון\" מאגד מאות חברות, ארגונים ועמותות שיחליפו את הלוגו שלהן לעיצוב המבוסס על כתב ידם של נופלי חרבות ברזל • השנה לוקחים חלק לראשונה עשרות מרכזי תרבות, אמנות ומוזיקה","content":"ONLY AVAILABLE IN PAID PLANS","keywords":["יום הזיכרון 2026"],"creator":["מאיה כהן"],"language":"hebrew","country":["israel"],"category":["lifestyle","top"],"datatype":"news","pubDate":"2026-04-21 03:41:32","pubDateTZ":"UTC","fetched_at":"2026-04-21 04:03:58","image_url":"https://www.israelhayom.co.il/wp-content/uploads/2026/04/20/20/WhatsApp-Image-2026-04-20-at-12.20.33-2.jpeg","video_url":null,"source_id":"israelhayom","source_name":"ישראל היום","source_priority":13660,"source_url":"https://www.israelhayom.co.il","source_icon":"https://n.bytvi.com/israelhayom.jpg","sentiment":"ONLY AVAILABLE IN PROFESSIONAL AND CORPORATE PLANS","sentiment_stats":"ONLY AVAILABLE IN PROFESSIONAL AND CORPORATE PLANS","ai_tag":"ONLY AVAILABLE IN PROFESSIONAL AND CORPORATE PLANS","ai_region":"ONLY AVAILABLE IN CORPORATE PLANS","ai_org":"ONLY AVAILABLE IN CORPORATE PLANS","ai_summary":"ONLY AVAILABLE IN PAID PLANS","duplicate":false},{"article_id":"f826557d704e46c70869a1ad488660e1","link":"https://www.haaretz.co.il/food/drinks/2026-04-21/ty-article-magazine/.premium/0000019d-a4d6-d096-a3df-eef7e6720000","title":"חַבֵּקותִי: שיתוף הפעולה של זאב אנגלמאיר ומבשלת מלכה הוליד בירה למנגל, ותזכורת חשובה","description":"במבשלת מלכה מציינים 20 שנה וגם 78 למדינה עם מהדורה חגיגית שכוללת איורים אופטימיים של המאייר זאב אנגלמאיר שמזכירים שבעת הזו וגם בכלל, כולם צריכים חיבוק. אולי גם בירה קרה","content":"ONLY AVAILABLE IN PAID PLANS","keywords":["בירה","יין ואלכוהול","משקאות"],"creator":["רוני קשמין"],"language":"hebrew","country":["israel"],"category":["lifestyle","top"],"datatype":"news","pubDate":"2026-04-21 03:40:24","pubDateTZ":"UTC","fetched_at":"2026-04-21 04:08:45","image_url":"https://img.haarets.co.il/bs/0000019d-a4dc-d096-a3df-eefd5d300001/d3/22/86176408431fb39b5b9f51a44abc/malka.jpg?height=81","video_url":null,"source_id":"haaretz","source_name":"Haaretz","source_priority":81949,"source_url":"https://www.haaretz.co.il","source_icon":"https://n.bytvi.com/haaretz.png","sentiment":"ONLY AVAILABLE IN PROFESSIONAL AND CORPORATE PLANS","sentiment_stats":"ONLY AVAILABLE IN PROFESSIONAL AND CORPORATE PLANS","ai_tag":"ONLY AVAILABLE IN PROFESSIONAL AND CORPORATE PLANS","ai_region":"ONLY AVAILABLE IN CORPORATE PLANS","ai_org":"ONLY AVAILABLE IN CORPORATE PLANS","ai_summary":"ONLY AVAILABLE IN PAID PLANS","duplicate":false},{"article_id":"b48ea096272de2298af77a2b03f910a5","link":"https://news.walla.co.il/item/3832190","title":"עלייה קלה בטמפרטורות, אך עדיין קר מהרגיל לעונה | התחזית ליום הזיכרון וערב יום העצמאות","description":"כשעם ישראל יפקוד את קברי יקיריו בבוקר, הטמפרטורות צפויות להיות נמוכות מהרגיל לעונה. המגמה תימשך גם מחר, יום העצמאות, ועד לסוף השבוע הקרוב","content":"ONLY AVAILABLE IN PAID PLANS","keywords":null,"creator":["יואב איתיאל"],"language":"hebrew","country":["israel"],"category":["lifestyle","top"],"datatype":"news","pubDate":"2026-04-21 03:35:25","pubDateTZ":"UTC","fetched_at":"2026-04-21 03:35:25","image_url":"https://images.wcdn.co.il/f_auto,q_auto,w_1200,t_54/4/0/4/0/4040485-46.jpg","video_url":null,"source_id":"walla","source_name":"Walla!","source_priority":26977,"source_url":"https://www.walla.co.il","source_icon":"https://n.bytvi.com/walla.png","sentiment":"ONLY AVAILABLE IN PROFESSIONAL AND CORPORATE PLANS","sentiment_stats":"ONLY AVAILABLE IN PROFESSIONAL AND CORPORATE PLANS","ai_tag":"ONLY AVAILABLE IN PROFESSIONAL AND CORPORATE PLANS","ai_region":"ONLY AVAILABLE IN CORPORATE PLANS","ai_org":"ONLY AVAILABLE IN CORPORATE PLANS","ai_summary":"ONLY AVAILABLE IN PAID PLANS","duplicate":false},{"article_id":"409d66b4dc1e749d8a1429184ef433b9","link":"https://www.ynet.co.il/news/article/bjpmdevabe","title":"מעצמת הגרעין שלא מכירה בישראל, אך למדה את \"שפת טראמפ\" והפכה למתווכת","description":"במשך שנה חיזרה פקיסטן אחר טראמפ, הרעיפה עליו שבחים והציעה הסכמים. לבסוף חתמה על עסקאות מינרלים וקריפטו, הצטרפה ל\"מועצת השלום\" וגם סיפקה מידע מודיעיני - וזכתה בתפקיד היוקרתי כמתווכת. אך סבל הפקיסטנים לא פחת, בצל משבר יוקר מחיה חמור: \"הכאב הכלכלי - מעבר לכל דמיון\". היחס לישראל כ\"פרוקסי של ארה\"ב\", והביקורת על אירוח המו\"מ: \"העיר מושבתת ימים\"","content":"ONLY AVAILABLE IN PAID PLANS","keywords":["איראן","פקיסטן","ארצות הברית","מלחמה","הפסקת אש","משא ומתן","מבצע שאגת הארי"],"creator":["ynet"],"language":"hebrew","country":["israel"],"category":["lifestyle","top"],"datatype":"news","pubDate":"2026-04-21 03:31:41","pubDateTZ":"UTC","fetched_at":"2026-04-21 04:00:58","image_url":"https://ynet-pic1.yit.co.il/picserver6/crop_images/2026/04/19/HJH4W9MaWg/HJH4W9MaWg_0_0_3000_2000_0_large.jpg","video_url":null,"source_id":"ynet_co","source_name":"Ynet Co Il Home","source_priority":7955,"source_url":"https://www.ynet.co.il","source_icon":"https://n.bytvi.com/ynet_co.png","sentiment":"ONLY AVAILABLE IN PROFESSIONAL AND CORPORATE PLANS","sentiment_stats":"ONLY AVAILABLE IN PROFESSIONAL AND CORPORATE PLANS","ai_tag":"ONLY AVAILABLE IN PROFESSIONAL AND CORPORATE PLANS","ai_region":"ONLY AVAILABLE IN CORPORATE PLANS","ai_org":"ONLY AVAILABLE IN CORPORATE PLANS","ai_summary":"ONLY AVAILABLE IN PAID PLANS","duplicate":false}],"nextPage":"1776742301189088711"}
